Workbook

Sheet Summary
A1: Five-Star Business Finance: NBFC Valuation Model
A2: Secured small-business lending to India's informal economy. Prepared as an assessment exercise; not investment advice.
A4: Scenario toggle (1 = Bear, 2 = Base, 3 = Bull) | C4: 2 | D4: =CHOOSE(C4,"Bear case","Base case","Bull case") -> Base case | E4: < selected
A6: HEADLINE (selected scenario) | D6: SCENARIO SETUPS | E6: Bear | F6: Base | G6: Bull
A7: Current share price (Rs) | B7: =Valuation!B5 -> 480 | D7: AUM growth | E7: =Assumptions!$B$5 -> 0.12 | F7: =Assumptions!$C$5 -> 0.19 | G7: =Assumptions!$D$5 -> 0.24
A8: Current market cap (Rs Cr) | B8: =Valuation!B7 -> 14140.8 | D8: Loan yield | E8: =Assumptions!$B$6 -> 0.23 | F8: =Assumptions!$C$6 -> 0.235 | G8: =Assumptions!$D$6 -> 0.24
A9: Expected IRR at current price (4-yr) | B9: =Valuation!B25 -> 0.22520173 | D9: Cost of funds | E9: =Assumptions!$B$7 -> 0.102 | F9: =Assumptions!$C$7 -> 0.097 | G9: =Assumptions!$D$7 -> 0.092
A10: Money multiple (MOIC) | B10: =Valuation!B26 -> 2.2440315 | D10: Opex / AUM | E10: =Assumptions!$B$10 -> 0.07 | F10: =Assumptions!$C$10 -> 0.064 | G10: =Assumptions!$D$10 -> 0.06
A11: Max entry price for 20% IRR (Rs) | B11: =Valuation!B28 -> 521.34068 | D11: Credit cost | E11: =Assumptions!$B$11 -> 0.023 | F11: =Assumptions!$C$11 -> 0.016 | G11: =Assumptions!$D$11 -> 0.013
A12: Upside / (downside) to max entry | B12: =Valuation!B29 -> 0.086126407 | D12: Exit P/E | E12: =Assumptions!$B$16 -> 10 | F12: =Assumptions!$C$16 -> 15 | G12: =Assumptions!$D$16 -> 18
A13: Exit P/E assumed (x) | B13: =Valuation!B9 -> 15
A14: Exit equity value FY30 (Rs Cr) | B14: =Valuation!B15 -> 31335.92
A15: Implied exit P/B (x) | B15: =Valuation!B16 -> 2.3021594
A17: MODEL HIGHLIGHTS (selected scenario)
A18: FY30 AUM (Rs Cr) | B18: =Model_PnL!F5 -> 26520.611
A19: FY30 PAT (Rs Cr) | B19: =Model_PnL!F24 -> 2089.0614
A20: PAT CAGR FY26 to FY30 | B20: =(Model_PnL!F24/Model_PnL!B24)^(1/4)-1 -> 0.17419
A21: Average ROA FY27 to FY30 | B21: =AVERAGE(Ratios!C14:F14) -> 0.074109297
A22: Average ROE FY27 to FY30 | B22: =AVERAGE(Ratios!C15:F15) -> 0.16177121
A23: FY30 debt-to-equity (x) | B23: =Ratios!F17 -> 1.2601354
A25: INVESTMENT VIEW
A26: - Five-Star is a best-in-class underwriter of informal-economy credit: ROA near 7% and yields above 24% on conservative leverage, with a 20-year, in-house, secured (3C) lending model.
A27: - FY26 profit was flat as management deliberately slowed disbursements to protect asset quality through a small-ticket credit-cycle stress; the model did not break and slippage is recovering.
A28: - The stock has de-rated ~30% on private-equity selling and the growth wobble, leaving it at the cheapest multiple in its peer set (~12x earnings, ~1.8x book) despite top-tier returns.
A29: - Base case clears the bar: with AUM growth near the ~20% guide and a re-rating toward ~15x earnings, the four-year IRR at the current price runs in the low-20s, leaving modest headroom on entry price (max entry ~Rs 520).
A30: - The result is highly sensitive to the exit multiple: a bull re-rate compounds to a high-30s IRR, while a bear de-rating to ~10x with slower growth leaves the return near zero. The multiple, in turn, tracks whether growth re-accelerates.
A31: - Risks to underwrite: a narrowing (replicable) moat, geographic concentration, wholesale-only funding, weak recovery tools (no SARFAESI below Rs 20 lakh), and a falling promoter stake as backers exit.
A32: - Verdict: a constructive accumulator at this valuation for investors who can underwrite the moat and tolerate the overhang; not a passive, wide-moat compounder.

Sheet Assumptions
A1: Five-Star Business Finance | Model Assumptions
A2: Rs Cr unless stated. Blue = input; black = formula; green = cross-sheet link. Scenario toggle on Summary.
A3: Driver | B3: Bear | C3: Base | D3: Bull | E3: Selected | F3: Notes
A4: OPERATING DRIVERS
A5: AUM growth (per year) | B5: 0.12 | C5: 0.19 | D5: 0.24 | E5: =CHOOSE(Summary!$C$4,B5,C5,D5) -> 0.19 | F5: FY27 management guide ~20%
A6: Loan yield (% of avg AUM) | B6: 0.23 | C6: 0.235 | D6: 0.24 | E6: =CHOOSE(Summary!$C$4,B6,C6,D6) -> 0.235 | F6: Gross portfolio yield, mid-20s
A7: Cost of funds (% of borrowings) | B7: 0.102 | C7: 0.097 | D7: 0.092 | E7: =CHOOSE(Summary!$C$4,B7,C7,D7) -> 0.097 | F7: Wholesale funding
A8: Cash & investment yield | B8: 0.06 | C8: 0.06 | D8: 0.06 | E8: =CHOOSE(Summary!$C$4,B8,C8,D8) -> 0.06 | F8: Treasury yield on buffer
A9: Other income (% of avg AUM) | B9: 0.005 | C9: 0.006 | D9: 0.007 | E9: =CHOOSE(Summary!$C$4,B9,C9,D9) -> 0.006 | F9: Fees and ancillary income
A10: Operating expenses (% of avg AUM) | B10: 0.07 | C10: 0.064 | D10: 0.06 | E10: =CHOOSE(Summary!$C$4,B10,C10,D10) -> 0.064 | F10: High-touch model
A11: Credit cost (% of avg AUM) | B11: 0.023 | C11: 0.016 | D11: 0.013 | E11: =CHOOSE(Summary!$C$4,B11,C11,D11) -> 0.016 | F11: FY26 ~1.9%; FY27 guide 1.7 to 1.75%
A12: Cash & investments (% of AUM) | B12: 0.18 | C12: 0.16 | D12: 0.14 | E12: =CHOOSE(Summary!$C$4,B12,C12,D12) -> 0.16 | F12: Liquidity buffer, declines over time
A13: Tax rate | B13: 0.25 | C13: 0.25 | D13: 0.25 | E13: =CHOOSE(Summary!$C$4,B13,C13,D13) -> 0.25 | F13: Effective tax ~25%
A14: Dividend payout | B14: 0.06 | C14: 0.06 | D14: 0.06 | E14: =CHOOSE(Summary!$C$4,B14,C14,D14) -> 0.06 | F14: ~Rs 2 per share on FY26 EPS
A15: VALUATION DRIVERS
A16: Exit P/E multiple | B16: 10 | C16: 15 | D16: 18 | E16: =CHOOSE(Summary!$C$4,B16,C16,D16) -> 15 | F16: Current ~12x; Base assumes modest re-rating
A17: Hold period (years) | B17: 4 | C17: 4 | D17: 4 | E17: =CHOOSE(Summary!$C$4,B17,C17,D17) -> 4 | F17: Four-year hold
A18: ANCHORS (FY26 actuals / market)
A19: Current share price (Rs) | B19: 480 | C19: 480 | D19: 480 | E19: =CHOOSE(Summary!$C$4,B19,C19,D19) -> 480 | F19: NSE, June 2026 (approx)
A20: Shares outstanding (Cr) | B20: 29.46 | C20: 29.46 | D20: 29.46 | E20: =CHOOSE(Summary!$C$4,B20,C20,D20) -> 29.46 | F20: ~29.5 crore shares
A21: FY26 AUM (Rs Cr) | B21: 13225 | C21: 13225 | D21: 13225 | E21: =CHOOSE(Summary!$C$4,B21,C21,D21) -> 13225 | F21: Reported FY26 AUM
A22: FY26 net worth (Rs Cr) | B22: 7400 | C22: 7400 | D22: 7400 | E22: =CHOOSE(Summary!$C$4,B22,C22,D22) -> 7400 | F22: Estimated FY26 closing net worth
A23: FY26 cash & investments (Rs Cr) | B23: 2645 | C23: 2645 | D23: 2645 | E23: =CHOOSE(Summary!$C$4,B23,C23,D23) -> 2645 | F23: ~20% of AUM

Sheet Model_PnL
A1: Five-Star Business Finance | Projection Model (Rs Cr)
A2: FY26 actual anchor; FY27 to FY30 driven by selected-scenario assumptions.
B3: FY26A | C3: FY27E | D3: FY28E | E3: FY29E | F3: FY30E
A4: AUM AND BALANCE SHEET
A5: AUM (closing) | B5: =Assumptions!$E$21 -> 13225 | C5: =B5*(1+Assumptions!$E$5) -> 15737.75 | D5: =C5*(1+Assumptions!$E$5) -> 18727.923 | E5: =D5*(1+Assumptions!$E$5) -> 22286.228 | F5: =E5*(1+Assumptions!$E$5) -> 26520.611
A6: Average AUM | C6: =(B5+C5)/2 -> 14481.375 | D6: =(C5+D5)/2 -> 17232.836 | E6: =(D5+E5)/2 -> 20507.075 | F6: =(E5+F5)/2 -> 24403.419
A7: Cash and investments | B7: =Assumptions!$E$23 -> 2645 | C7: =C5*Assumptions!$E$12 -> 2518.04 | D7: =D5*Assumptions!$E$12 -> 2996.4676 | E7: =E5*Assumptions!$E$12 -> 3565.7964 | F7: =F5*Assumptions!$E$12 -> 4243.2978
A8: Total assets | B8: =B5+B7 -> 15870 | C8: =C5+C7 -> 18255.79 | D8: =D5+D7 -> 21724.39 | E8: =E5+E7 -> 25852.024 | F8: =F5+F7 -> 30763.909
A9: Net worth (closing) | B9: =Assumptions!$E$22 -> 7400 | C9: =B9+C24-C25 -> 8573.6858 | D9: =C9+D24-D25 -> 9984.22 | E9: =D9+E24-E25 -> 11647.816 | F9: =E9+F24-F25 -> 13611.534
A10: Borrowings (closing) | B10: =B8-B9 -> 8470 | C10: =C8-C9 -> 9682.1042 | D10: =D8-D9 -> 11740.17 | E10: =E8-E9 -> 14204.208 | F10: =F8-F9 -> 17152.375
A12: PROFIT AND LOSS
A13: Interest income - loans | C13: =C6*Assumptions!$E$6 -> 3403.1231 | D13: =D6*Assumptions!$E$6 -> 4049.7165 | E13: =E6*Assumptions!$E$6 -> 4819.1627 | F13: =F6*Assumptions!$E$6 -> 5734.8036
A14: Interest income - cash and investments | C14: =((B7+C7)/2)*Assumptions!$E$8 -> 154.8912 | D14: =((C7+D7)/2)*Assumptions!$E$8 -> 165.43523 | E14: =((D7+E7)/2)*Assumptions!$E$8 -> 196.86792 | F14: =((E7+F7)/2)*Assumptions!$E$8 -> 234.27283
A15: Total interest income | C15: =C13+C14 -> 3558.0143 | D15: =D13+D14 -> 4215.1517 | E15: =E13+E14 -> 5016.0306 | F15: =F13+F14 -> 5969.0764
A16: Interest expense (on opening borrowings) | C16: =-B10*Assumptions!$E$7 -> -821.59 | D16: =-C10*Assumptions!$E$7 -> -939.16411 | E16: =-D10*Assumptions!$E$7 -> -1138.7965 | F16: =-E10*Assumptions!$E$7 -> -1377.8082
A17: Net interest income (NII) | C17: =C15+C16 -> 2736.4243 | D17: =D15+D16 -> 3275.9876 | E17: =E15+E16 -> 3877.2341 | F17: =F15+F16 -> 4591.2682
A18: Other income | C18: =C6*Assumptions!$E$9 -> 86.88825 | D18: =D6*Assumptions!$E$9 -> 103.39702 | E18: =E6*Assumptions!$E$9 -> 123.04245 | F18: =F6*Assumptions!$E$9 -> 146.42052
A19: Net total income | B19: 3218 | C19: =C17+C18 -> 2823.3126 | D19: =D17+D18 -> 3379.3847 | E19: =E17+E18 -> 4000.2765 | F19: =F17+F18 -> 4737.6887
A20: Operating expenses | C20: =-C6*Assumptions!$E$10 -> -926.808 | D20: =-D6*Assumptions!$E$10 -> -1102.9015 | E20: =-E6*Assumptions!$E$10 -> -1312.4528 | F20: =-F6*Assumptions!$E$10 -> -1561.8188
A21: Pre-provision operating profit (PPOP) | C21: =C19+C20 -> 1896.5046 | D21: =D19+D20 -> 2276.4831 | E21: =E19+E20 -> 2687.8237 | F21: =F19+F20 -> 3175.8699
A22: Credit cost (provisions) | C22: =-C6*Assumptions!$E$11 -> -231.702 | D22: =-D6*Assumptions!$E$11 -> -275.72538 | E22: =-E6*Assumptions!$E$11 -> -328.1132 | F22: =-F6*Assumptions!$E$11 -> -390.45471
A23: Profit before tax | C23: =C21+C22 -> 1664.8026 | D23: =D21+D22 -> 2000.7578 | E23: =E21+E22 -> 2359.7105 | F23: =F21+F22 -> 2785.4152
A24: Profit after tax (PAT) | B24: 1099 | C24: =C23*(1-Assumptions!$E$13) -> 1248.6019 | D24: =D23*(1-Assumptions!$E$13) -> 1500.5683 | E24: =E23*(1-Assumptions!$E$13) -> 1769.7829 | F24: =F23*(1-Assumptions!$E$13) -> 2089.0614
A25: Dividends paid | B25: 59 | C25: =C24*Assumptions!$E$14 -> 74.916116 | D25: =D24*Assumptions!$E$14 -> 90.034099 | E25: =E24*Assumptions!$E$14 -> 106.18697 | F25: =F24*Assumptions!$E$14 -> 125.34368
A27: Memo: EPS (Rs) | B27: =B24/Assumptions!$E$20 -> 37.30482 | C27: =C24/Assumptions!$E$20 -> 42.382958 | D27: =D24/Assumptions!$E$20 -> 50.935788 | E27: =E24/Assumptions!$E$20 -> 60.074097 | F27: =F24/Assumptions!$E$20 -> 70.911791
A28: Memo: tax | C28: =-C23*Assumptions!$E$13 -> -416.20064 | D28: =-D23*Assumptions!$E$13 -> -500.18944 | E28: =-E23*Assumptions!$E$13 -> -589.92763 | F28: =-F23*Assumptions!$E$13 -> -696.35379
A30: Note: interest expense uses opening (prior-year closing) borrowings to avoid circularity. FY26 P&L shows reported headline only.

Sheet Ratios
A1: Five-Star Business Finance | Key Ratios
A2: Profitability, margins, efficiency and leverage. Green = pulled from Model_PnL.
B3: FY26A | C3: FY27E | D3: FY28E | E3: FY29E | F3: FY30E
A4: GROWTH
A5: AUM growth | C5: =Model_PnL!C5/Model_PnL!B5-1 -> 0.19 | D5: =Model_PnL!D5/Model_PnL!C5-1 -> 0.19 | E5: =Model_PnL!E5/Model_PnL!D5-1 -> 0.19 | F5: =Model_PnL!F5/Model_PnL!E5-1 -> 0.19
A6: PAT growth | C6: =Model_PnL!C24/Model_PnL!B24-1 -> 0.13612551 | D6: =Model_PnL!D24/Model_PnL!C24-1 -> 0.20179881 | E6: =Model_PnL!E24/Model_PnL!D24-1 -> 0.17940841 | F6: =Model_PnL!F24/Model_PnL!E24-1 -> 0.18040545
A7: MARGINS (% of average AUM)
A8: Loan yield | C8: =Model_PnL!C13/Model_PnL!C6 -> 0.235 | D8: =Model_PnL!D13/Model_PnL!D6 -> 0.235 | E8: =Model_PnL!E13/Model_PnL!E6 -> 0.235 | F8: =Model_PnL!F13/Model_PnL!F6 -> 0.235
A9: Net interest margin | C9: =Model_PnL!C17/Model_PnL!C6 -> 0.18896164 | D9: =Model_PnL!D17/Model_PnL!D6 -> 0.19010148 | E9: =Model_PnL!E17/Model_PnL!E6 -> 0.18906812 | F9: =Model_PnL!F17/Model_PnL!F6 -> 0.18814036
A10: Cost of funds (on avg borrowings) | C10: =-Model_PnL!C16/((Model_PnL!B10+Model_PnL!C10)/2) -> 0.090522839 | D10: =-Model_PnL!D16/((Model_PnL!C10+Model_PnL!D10)/2) -> 0.087681083 | E10: =-Model_PnL!E16/((Model_PnL!D10+Model_PnL!E10)/2) -> 0.087787534 | F10: =-Model_PnL!F16/((Model_PnL!E10+Model_PnL!F10)/2) -> 0.087879995
A11: Credit cost | C11: =-Model_PnL!C22/Model_PnL!C6 -> 0.016 | D11: =-Model_PnL!D22/Model_PnL!D6 -> 0.016 | E11: =-Model_PnL!E22/Model_PnL!E6 -> 0.016 | F11: =-Model_PnL!F22/Model_PnL!F6 -> 0.016
A12: EFFICIENCY AND RETURNS
A13: Cost-to-income | C13: =-Model_PnL!C20/Model_PnL!C19 -> 0.32826971 | D13: =-Model_PnL!D20/Model_PnL!D19 -> 0.32636164 | E13: =-Model_PnL!E20/Model_PnL!E19 -> 0.32809052 | F13: =-Model_PnL!F20/Model_PnL!F19 -> 0.32965839
A14: Return on assets | C14: =Model_PnL!C24/((Model_PnL!B8+Model_PnL!C8)/2) -> 0.073176441 | D14: =Model_PnL!D24/((Model_PnL!C8+Model_PnL!D8)/2) -> 0.075065611 | E14: =Model_PnL!E24/((Model_PnL!D8+Model_PnL!E8)/2) -> 0.074397489 | F14: =Model_PnL!F24/((Model_PnL!E8+Model_PnL!F8)/2) -> 0.073797648
A15: Return on equity | C15: =Model_PnL!C24/((Model_PnL!B9+Model_PnL!C9)/2) -> 0.15633235 | D15: =Model_PnL!D24/((Model_PnL!C9+Model_PnL!D9)/2) -> 0.16171742 | E15: =Model_PnL!E24/((Model_PnL!D9+Model_PnL!E9)/2) -> 0.1636261 | F15: =Model_PnL!F24/((Model_PnL!E9+Model_PnL!F9)/2) -> 0.16540896
A16: LEVERAGE AND PER-SHARE
A17: Debt-to-equity (closing) | B17: =Model_PnL!B10/Model_PnL!B9 -> 1.1445946 | C17: =Model_PnL!C10/Model_PnL!C9 -> 1.1292814 | D17: =Model_PnL!D10/Model_PnL!D9 -> 1.1758725 | E17: =Model_PnL!E10/Model_PnL!E9 -> 1.219474 | F17: =Model_PnL!F10/Model_PnL!F9 -> 1.2601354
A18: EPS (Rs) | B18: =Model_PnL!B24/Assumptions!$E$20 -> 37.30482 | C18: =Model_PnL!C24/Assumptions!$E$20 -> 42.382958 | D18: =Model_PnL!D24/Assumptions!$E$20 -> 50.935788 | E18: =Model_PnL!E24/Assumptions!$E$20 -> 60.074097 | F18: =Model_PnL!F24/Assumptions!$E$20 -> 70.911791
A19: Book value per share (Rs) | B19: =Model_PnL!B9/Assumptions!$E$20 -> 251.18805 | C19: =Model_PnL!C9/Assumptions!$E$20 -> 291.02803 | D19: =Model_PnL!D9/Assumptions!$E$20 -> 338.90767 | E19: =Model_PnL!E9/Assumptions!$E$20 -> 395.37732 | F19: =Model_PnL!F9/Assumptions!$E$20 -> 462.03441
A20: Dividend per share (Rs) | B20: =Model_PnL!B25/Assumptions!$E$20 -> 2.0027155 | C20: =Model_PnL!C25/Assumptions!$E$20 -> 2.5429775 | D20: =Model_PnL!D25/Assumptions!$E$20 -> 3.0561473 | E20: =Model_PnL!E25/Assumptions!$E$20 -> 3.6044458 | F20: =Model_PnL!F25/Assumptions!$E$20 -> 4.2547075

Sheet Valuation
A1: Five-Star Business Finance | Valuation and IRR
A2: Four-year hold, exit on FY30 earnings. Max entry price solves for a 20% IRR.
A4: INPUTS
A5: Current share price (Rs) | B5: =Assumptions!$E$19 -> 480
A6: Shares outstanding (Cr) | B6: =Assumptions!$E$20 -> 29.46
A7: Current market cap (Rs Cr) | B7: =B5*B6 -> 14140.8
A8: Hold period (years) | B8: =Assumptions!$E$17 -> 4
A9: Exit P/E multiple | B9: =Assumptions!$E$16 -> 15
A10: Hurdle rate (target IRR) | B10: 0.2 | C10: Input: required return
A12: EXIT VALUE (END OF FY30)
A13: Exit-year PAT (FY30, Rs Cr) | B13: =Model_PnL!F24 -> 2089.0614
A14: Exit-year net worth (FY30, Rs Cr) | B14: =Model_PnL!F9 -> 13611.534
A15: Exit equity value (Rs Cr) | B15: =B9*B13 -> 31335.92
A16: Implied exit P/B (x) | B16: =B15/B14 -> 2.3021594
A18: CASH FLOWS TO EQUITY (Rs Cr)
A19: Year | B19: 0 (now) | C19: 1 (FY27) | D19: 2 (FY28) | E19: 3 (FY29) | F19: 4 (FY30)
A20: Dividends | B20: 0 | C20: =Model_PnL!C25 -> 74.916116 | D20: =Model_PnL!D25 -> 90.034099 | E20: =Model_PnL!E25 -> 106.18697 | F20: =Model_PnL!F25 -> 125.34368
A21: Entry / exit equity | B21: =-B7 -> -14140.8 | C21: 0 | D21: 0 | E21: 0 | F21: =B15 -> 31335.92
A22: Net cash flow | B22: =B20+B21 -> -14140.8 | C22: =C20+C21 -> 74.916116 | D22: =D20+D21 -> 90.034099 | E22: =E20+E21 -> 106.18697 | F22: =F20+F21 -> 31461.264
A24: RESULTS
A25: Expected IRR at current price (4-yr) | B25: =IRR(B22:F22) -> 0.22520173
A26: Money multiple (MOIC) | B26: =(SUM(C20:F20)+B15)/B7 -> 2.2440315
A27: Max entry market cap for 20% IRR (Rs Cr) | B27: =NPV(B10,C22:F22) -> 15358.696
A28: Max entry price for 20% IRR (Rs) | B28: =B27/B6 -> 521.34068
A29: Upside / (downside) to max entry | B29: =B28/B5-1 -> 0.086126407
A31: SENSITIVITY | exit P/E versus outcome
A32: Exit P/E (x) | B32: 10 | C32: 12 | D32: 14 | E32: 16 | F32: 18
A33: Exit equity value (Rs Cr) | B33: =B32*$B$13 -> 20890.614 | C33: =C32*$B$13 -> 25068.736 | D33: =D32*$B$13 -> 29246.859 | E33: =E32*$B$13 -> 33424.982 | F33: =F32*$B$13 -> 37603.105
A34: Max entry price for 20% IRR (Rs) | B34: =(NPV($B$10,$C$20:$F$20)+B33/(1+$B$10)^$B$8)/$B$6 -> 350.35353 | C34: =(NPV($B$10,$C$20:$F$20)+C33/(1+$B$10)^$B$8)/$B$6 -> 418.74839 | D34: =(NPV($B$10,$C$20:$F$20)+D33/(1+$B$10)^$B$8)/$B$6 -> 487.14325 | E34: =(NPV($B$10,$C$20:$F$20)+E33/(1+$B$10)^$B$8)/$B$6 -> 555.53811 | F34: =(NPV($B$10,$C$20:$F$20)+F33/(1+$B$10)^$B$8)/$B$6 -> 623.93297
A35: IRR at current price (approx, 4-yr) | B35: =((SUM($C$20:$F$20)+B33)/$B$7)^(1/$B$8)-1 -> 0.10767053 | C35: =((SUM($C$20:$F$20)+C33)/$B$7)^(1/$B$8)-1 -> 0.15842615 | D35: =((SUM($C$20:$F$20)+D33)/$B$7)^(1/$B$8)-1 -> 0.20327055 | E35: =((SUM($C$20:$F$20)+E33)/$B$7)^(1/$B$8)-1 -> 0.24359682 | F35: =((SUM($C$20:$F$20)+F33)/$B$7)^(1/$B$8)-1 -> 0.28034267
A37: Approximate IRR treats dividends as received at exit; the headline IRR above uses dated cash flows.
