Workbook

Sheet 1. Cover
B4: — TARGET DEEP-DIVE
B6: Mswipe Technologies — Bottoms-Up Valuation Model
B10: A discussion document accompanying the Project Pinnacle strategy deck.
B13: INVESTMENT THESIS — WHY MSWIPE
B15: 1. Distressed asset | C15: Last priced at $210M in 2017; capital-starved since 2024 bridge round; willing seller.
B16: 2. #3 offline mPOS scale | C16: ~700K merchants, 16,000 pin codes, ₹342 Cr FY25 revenue — #3 after Pine Labs and BharatPe.
B17: 3. Defensive consolidation | C17: Removes the #3 competitor and lifts Pine Labs offline market share from ~38% → ~50%.
B18: 4. Cost synergy clarity | C18: ~₹160 Cr run-rate cost synergies from terminal SKU consolidation, cloud / BD / G&A overlap.
B19: 5. Mcapital optionality | C19: Mswipe's lending license + ~700K merchant data = adjacent fintech revenue stream.
B20: 6. Actionable timeline | C20: Distressed seller + clear synergy logic = highest-conviction, lowest-execution-risk deal.
B23: COLOR CONVENTIONS
B25: Hardcoded inputs | D25: 1,234
B26: Formulas / calculations | D26: B5 * C10
B27: Cross-sheet links | D27: '2. Operating Assumptions'!B10
B30: MODEL CONTENTS
B32: 1. Cover | D32: This page
B33: 2. Operating Assumptions | D33: Merchant counts, GTV, take rates, terminal economics
B34: 3. Revenue Build | D34: Bottoms-up revenue by segment (acquiring, terminal, lending, VAS)
B35: 4. Cost Build | D35: Variable + fixed cost stack with unit economics
B36: 5. P&L Forecast | D36: FY22–FY30 income statement
B37: 6. DCF Valuation | D37: 5-year explicit forecast + terminal value (Gordon Growth)
B38: 7. Trading Comps | D38: Listed payments / fintech comparables with multiples
B39: 8. Transaction Comps | D39: Precedent M&A transactions in payments
B40: 9. Football Field | D40: Valuation range across methodologies
B41: 10. Deal Structure | D41: Sources & uses, financing, control premium
B42: 11. Sensitivity | D42: Two-way tables: WACC × TGR, take rate × merchant growth
B45: KEY DATA SOURCES
B47: • Mswipe MCA / RoC filings: FY22 (₹230 Cr), FY23 (₹274 Cr), FY24 (₹277 Cr revenue, ₹46 Cr loss)
B48: • Mswipe FY25 Tracxn / Inc42 data: ₹342 Cr revenue (+21% YoY); EBITDA margin ~2%
B49: • Mswipe public press: Series F bridge Feb 2024 ($20M from existing investors), last mark $210M (2017)
B50: • Operating data: 700K merchants, 16,000 pin codes, 60K daily transactions/terminal (industry data)
B51: • Comps: Pine Labs IPO RHP (Nov 2025), Razorpay/Cashfree public reports, FactSet trading data
B52: • Precedent transactions: Worldline-Bambora, FIS-Worldpay, Innoviti-PayMate, Pine Labs-Mosambee
B55: IMPORTANT
B56: This model is illustrative and for discussion purposes only. Segment-level revenue splits are analyst estimates based on Mswipe's published financials, public statements, and industry benchmarks. Synergy estimates would be subject to detailed due diligence and management access.

Sheet 2. Operating Assumptions
A1: Mswipe — Operating Assumptions
A2: All inputs in blue. Current model state: standalone forecast (pre-acquisition).
C4: FY22A | D4: FY23A | E4: FY24A | F4: FY25A | G4: FY26E | H4: FY27E | I4: FY28E | J4: FY29E | K4: FY30E | L4: Source / Notes
A6: MERCHANT BASE & DISTRIBUTION
A8: Active merchants (thousands) | C8: 550 | D8: 620 | E8: 660 | F8: 700 | G8: =F8*(1+G9) -> 784 | H8: =G8*(1+H9) -> 862.4 | I8: =H8*(1+I9) -> 931.392 | J8: =I8*(1+J9) -> 996.58944 | K8: =J8*(1+K9) -> 1046.4189 | L8: Hist: Mswipe public statements; Fcst: post-deal stabilization
A9: Merchant growth (% YoY) | G9: 0.12 | H9: 0.1 | I9: 0.08 | J9: 0.07 | K9: 0.05
A10: Average merchants (year, '000) | C10: =C8 -> 550 | D10: =AVERAGE(C8,D8) -> 585 | E10: =AVERAGE(D8,E8) -> 640 | F10: =AVERAGE(E8,F8) -> 680 | G10: =AVERAGE(F8,G8) -> 742 | H10: =AVERAGE(G8,H8) -> 823.2 | I10: =AVERAGE(H8,I8) -> 896.896 | J10: =AVERAGE(I8,J8) -> 963.99072 | K10: =AVERAGE(J8,K8) -> 1021.5042
A12: Terminals per merchant (avg) | C12: 1.05 | D12: 1.1 | E12: 1.15 | F12: 1.18 | G12: 1.2 | H12: 1.22 | I12: 1.24 | J12: 1.26 | K12: 1.27
A13: Active terminals ('000) | C13: =C10*C12 -> 577.5 | D13: =D10*D12 -> 643.5 | E13: =E10*E12 -> 736 | F13: =F10*F12 -> 802.4 | G13: =G10*G12 -> 890.4 | H13: =H10*H12 -> 1004.304 | I13: =I10*I12 -> 1112.151 | J13: =J10*J12 -> 1214.6283 | K13: =K10*K12 -> 1297.3103
A15: GTV & PAYMENTS ECONOMICS
A17: Monthly GTV per terminal (₹ '000) | C17: 38 | D17: 45 | E17: 50 | F17: 55 | G17: 60 | H17: 65 | I17: 70 | J17: 75 | K17: 80 | L17: Industry: Pine Labs ~₹2L; Mswipe SME-skewed lower
A18: Total GTV (₹ Cr) | C18: =C13*C17*12/10 -> 26334 | D18: =D13*D17*12/10 -> 34749 | E18: =E13*E17*12/10 -> 44160 | F18: =F13*F17*12/10 -> 52958.4 | G18: =G13*G17*12/10 -> 64108.8 | H18: =H13*H17*12/10 -> 78335.712 | I18: =I13*I17*12/10 -> 93420.687 | J18: =J13*J17*12/10 -> 109316.55 | K18: =K13*K17*12/10 -> 124541.79
A20: MDR — net take rate (bps) | C20: 45 | D20: 42 | E20: 40 | F20: 38 | G20: 38 | H20: 37 | I20: 36 | J20: 35 | K20: 35 | L20: Net of interchange, scheme fees — illustrative
A22: MCAPITAL — LENDING ECONOMICS
A24: % merchants with active loan | C24: 0.02 | D24: 0.03 | E24: 0.04 | F24: 0.05 | G24: 0.06 | H24: 0.07 | I24: 0.08 | J24: 0.09 | K24: 0.1
A25: Avg loan ticket (₹ '000) | C25: 80 | D25: 90 | E25: 100 | F25: 110 | G25: 120 | H25: 130 | I25: 140 | J25: 150 | K25: 160
A26: Loan book (₹ Cr) | C26: =C10*C24*C25/10 -> 88 | D26: =D10*D24*D25/10 -> 157.95 | E26: =E10*E24*E25/10 -> 256 | F26: =F10*F24*F25/10 -> 374 | G26: =G10*G24*G25/10 -> 534.24 | H26: =H10*H24*H25/10 -> 749.112 | I26: =I10*I24*I25/10 -> 1004.5235 | J26: =J10*J24*J25/10 -> 1301.3875 | K26: =K10*K24*K25/10 -> 1634.4067
A27: Net interest spread (% on book) | C27: 0.08 | D27: 0.08 | E27: 0.09 | F27: 0.09 | G27: 0.1 | H27: 0.1 | I27: 0.1 | J27: 0.1 | K27: 0.1
A29: VAS & TERMINAL SALES
A31: Terminal sales (units, '000) | C31: 25 | D31: 35 | E31: 45 | F31: 50 | G31: 55 | H31: 60 | I31: 65 | J31: 70 | K31: 75
A32: Avg terminal sale price (₹ '000) | C32: 9 | D32: 9 | E32: 9.5 | F32: 10 | G32: 10 | H32: 10 | I32: 10.5 | J32: 11 | K32: 11
A33: VAS / subscription ARPU (₹ / merchant / yr) | C33: 250 | D33: 350 | E33: 450 | F33: 600 | G33: 700 | H33: 800 | I33: 900 | J33: 1000 | K33: 1100
A35: COST DRIVERS
A37: Variable cost (% of MDR revenue) | C37: 0.35 | D37: 0.34 | E37: 0.33 | F37: 0.32 | G37: 0.3 | H37: 0.28 | I37: 0.27 | J37: 0.26 | K37: 0.25 | L37: Interchange, processing, network fees passthrough
A38: Terminal COGS (% of terminal sale) | C38: 0.78 | D38: 0.78 | E38: 0.78 | F38: 0.78 | G38: 0.78 | H38: 0.78 | I38: 0.78 | J38: 0.78 | K38: 0.78
A39: Employee cost (₹ Cr) | C39: 85 | D39: 100 | E39: 115 | F39: 130 | G39: 150 | H39: 175 | I39: 200 | J39: 225 | K39: 250
A40: Other opex (₹ Cr) | C40: 45 | D40: 55 | E40: 70 | F40: 80 | G40: 92 | H40: 108 | I40: 128 | J40: 150 | K40: 175
A41: D&A (% of revenue) | C41: 0.1 | D41: 0.09 | E41: 0.08 | F41: 0.08 | G41: 0.07 | H41: 0.07 | I41: 0.07 | J41: 0.06 | K41: 0.06
A42: Capex (% of revenue) | C42: 0.12 | D42: 0.1 | E42: 0.08 | F42: 0.07 | G42: 0.06 | H42: 0.06 | I42: 0.05 | J42: 0.05 | K42: 0.05
A43: NWC change (% of Δrev) | C43: 0.1 | D43: 0.1 | E43: 0.1 | F43: 0.1 | G43: 0.1 | H43: 0.1 | I43: 0.1 | J43: 0.1 | K43: 0.1
A44: Effective tax rate | C44: 0 | D44: 0 | E44: 0 | F44: 0 | G44: 0 | H44: 0.05 | I44: 0.15 | J44: 0.22 | K44: 0.25
A46: VALUATION PARAMETERS
A48: WACC | C48: 0.13 | L48: Equity risk premium 7%, beta 1.3, Rf 6.5%
A49: Terminal growth rate | C49: 0.04 | L49: India long-term real GDP + inflation ~ 4%
A50: Exit multiple (EV/EBITDA) | C50: 12 | L50: Sensitivity input for exit-multiple method
A51: Forecast period (years) | C51: 5 | L51: FY26E–FY30E
A52: Control premium | C52: 0.1 | L52: Typical for distressed control deals
A53: Synergy share to seller (%) | C53: 0.25 | L53: PA standard: 20–30% of run-rate value to seller

Sheet 3. Revenue Build
A1: Mswipe — Revenue Build by Segment
A2: Bottoms-up: MDR + Mcapital + Terminal + VAS. Reconciles to reported figures.
C4: FY22A | D4: FY23A | E4: FY24A | F4: FY25A | G4: FY26E | H4: FY27E | I4: FY28E | J4: FY29E | K4: FY30E
A6: 1. MDR / ACQUIRING REVENUE
A8: GTV (₹ Cr) | C8: ='2. Operating Assumptions'!C18 -> 26334 | D8: ='2. Operating Assumptions'!D18 -> 34749 | E8: ='2. Operating Assumptions'!E18 -> 44160 | F8: ='2. Operating Assumptions'!F18 -> 52958.4 | G8: ='2. Operating Assumptions'!G18 -> 64108.8 | H8: ='2. Operating Assumptions'!H18 -> 78335.712 | I8: ='2. Operating Assumptions'!I18 -> 93420.687 | J8: ='2. Operating Assumptions'!J18 -> 109316.55 | K8: ='2. Operating Assumptions'!K18 -> 124541.79
A9: Take rate (bps) | C9: ='2. Operating Assumptions'!C20 -> 45 | D9: ='2. Operating Assumptions'!D20 -> 42 | E9: ='2. Operating Assumptions'!E20 -> 40 | F9: ='2. Operating Assumptions'!F20 -> 38 | G9: ='2. Operating Assumptions'!G20 -> 38 | H9: ='2. Operating Assumptions'!H20 -> 37 | I9: ='2. Operating Assumptions'!I20 -> 36 | J9: ='2. Operating Assumptions'!J20 -> 35 | K9: ='2. Operating Assumptions'!K20 -> 35
A10: MDR revenue (₹ Cr) | C10: =C8*C9/10000 -> 118.503 | D10: =D8*D9/10000 -> 145.9458 | E10: =E8*E9/10000 -> 176.64 | F10: =F8*F9/10000 -> 201.24192 | G10: =G8*G9/10000 -> 243.61344 | H10: =H8*H9/10000 -> 289.84213 | I10: =I8*I9/10000 -> 336.31447 | J10: =J8*J9/10000 -> 382.60792 | K10: =K8*K9/10000 -> 435.89626
A12: 2. MCAPITAL — LENDING REVENUE
A14: Avg loan book (₹ Cr) | C14: ='2. Operating Assumptions'!C26 -> 88 | D14: ='2. Operating Assumptions'!D26 -> 157.95 | E14: ='2. Operating Assumptions'!E26 -> 256 | F14: ='2. Operating Assumptions'!F26 -> 374 | G14: ='2. Operating Assumptions'!G26 -> 534.24 | H14: ='2. Operating Assumptions'!H26 -> 749.112 | I14: ='2. Operating Assumptions'!I26 -> 1004.5235 | J14: ='2. Operating Assumptions'!J26 -> 1301.3875 | K14: ='2. Operating Assumptions'!K26 -> 1634.4067
A15: Net interest spread | C15: ='2. Operating Assumptions'!C27 -> 0.08 | D15: ='2. Operating Assumptions'!D27 -> 0.08 | E15: ='2. Operating Assumptions'!E27 -> 0.09 | F15: ='2. Operating Assumptions'!F27 -> 0.09 | G15: ='2. Operating Assumptions'!G27 -> 0.1 | H15: ='2. Operating Assumptions'!H27 -> 0.1 | I15: ='2. Operating Assumptions'!I27 -> 0.1 | J15: ='2. Operating Assumptions'!J27 -> 0.1 | K15: ='2. Operating Assumptions'!K27 -> 0.1
A16: Lending revenue (₹ Cr) | C16: =C14*C15 -> 7.04 | D16: =D14*D15 -> 12.636 | E16: =E14*E15 -> 23.04 | F16: =F14*F15 -> 33.66 | G16: =G14*G15 -> 53.424 | H16: =H14*H15 -> 74.9112 | I16: =I14*I15 -> 100.45235 | J16: =J14*J15 -> 130.13875 | K16: =K14*K15 -> 163.44067
A18: 3. TERMINAL SALES
A20: Terminal units sold ('000) | C20: ='2. Operating Assumptions'!C31 -> 25 | D20: ='2. Operating Assumptions'!D31 -> 35 | E20: ='2. Operating Assumptions'!E31 -> 45 | F20: ='2. Operating Assumptions'!F31 -> 50 | G20: ='2. Operating Assumptions'!G31 -> 55 | H20: ='2. Operating Assumptions'!H31 -> 60 | I20: ='2. Operating Assumptions'!I31 -> 65 | J20: ='2. Operating Assumptions'!J31 -> 70 | K20: ='2. Operating Assumptions'!K31 -> 75
A21: Avg sale price (₹ '000) | C21: ='2. Operating Assumptions'!C32 -> 9 | D21: ='2. Operating Assumptions'!D32 -> 9 | E21: ='2. Operating Assumptions'!E32 -> 9.5 | F21: ='2. Operating Assumptions'!F32 -> 10 | G21: ='2. Operating Assumptions'!G32 -> 10 | H21: ='2. Operating Assumptions'!H32 -> 10 | I21: ='2. Operating Assumptions'!I32 -> 10.5 | J21: ='2. Operating Assumptions'!J32 -> 11 | K21: ='2. Operating Assumptions'!K32 -> 11
A22: Terminal sales revenue (₹ Cr) | C22: =C20*C21/10 -> 22.5 | D22: =D20*D21/10 -> 31.5 | E22: =E20*E21/10 -> 42.75 | F22: =F20*F21/10 -> 50 | G22: =G20*G21/10 -> 55 | H22: =H20*H21/10 -> 60 | I22: =I20*I21/10 -> 68.25 | J22: =J20*J21/10 -> 77 | K22: =K20*K21/10 -> 82.5
A24: 4. VAS / SUBSCRIPTION REVENUE
A26: Avg merchants ('000) | C26: ='2. Operating Assumptions'!C10 -> 550 | D26: ='2. Operating Assumptions'!D10 -> 585 | E26: ='2. Operating Assumptions'!E10 -> 640 | F26: ='2. Operating Assumptions'!F10 -> 680 | G26: ='2. Operating Assumptions'!G10 -> 742 | H26: ='2. Operating Assumptions'!H10 -> 823.2 | I26: ='2. Operating Assumptions'!I10 -> 896.896 | J26: ='2. Operating Assumptions'!J10 -> 963.99072 | K26: ='2. Operating Assumptions'!K10 -> 1021.5042
A27: VAS ARPU (₹ / merchant / yr) | C27: ='2. Operating Assumptions'!C33 -> 250 | D27: ='2. Operating Assumptions'!D33 -> 350 | E27: ='2. Operating Assumptions'!E33 -> 450 | F27: ='2. Operating Assumptions'!F33 -> 600 | G27: ='2. Operating Assumptions'!G33 -> 700 | H27: ='2. Operating Assumptions'!H33 -> 800 | I27: ='2. Operating Assumptions'!I33 -> 900 | J27: ='2. Operating Assumptions'!J33 -> 1000 | K27: ='2. Operating Assumptions'!K33 -> 1100
A28: VAS / Subscription revenue (₹ Cr) | C28: =C26*C27/10000 -> 13.75 | D28: =D26*D27/10000 -> 20.475 | E28: =E26*E27/10000 -> 28.8 | F28: =F26*F27/10000 -> 40.8 | G28: =G26*G27/10000 -> 51.94 | H28: =H26*H27/10000 -> 65.856 | I28: =I26*I27/10000 -> 80.72064 | J28: =J26*J27/10000 -> 96.399072 | K28: =K26*K27/10000 -> 112.36546
A30: TOTAL REVENUE
A32: Total revenue (₹ Cr) | C32: =C10+C16+C22+C28 -> 161.793 | D32: =D10+D16+D22+D28 -> 210.5568 | E32: =E10+E16+E22+E28 -> 271.23 | F32: =F10+F16+F22+F28 -> 325.70192 | G32: =G10+G16+G22+G28 -> 403.97744 | H32: =H10+H16+H22+H28 -> 490.60933 | I32: =I10+I16+I22+I28 -> 585.73747 | J32: =J10+J16+J22+J28 -> 686.14574 | K32: =K10+K16+K22+K28 -> 794.20239
A33: Revenue growth (YoY) | D33: =IFERROR(D32/C32-1,0) -> 0.30139623 | E33: =IFERROR(E32/D32-1,0) -> 0.28815598 | F33: =IFERROR(F32/E32-1,0) -> 0.20083295 | G33: =IFERROR(G32/F32-1,0) -> 0.2403287 | H33: =IFERROR(H32/G32-1,0) -> 0.21444736 | I33: =IFERROR(I32/H32-1,0) -> 0.19389793 | J33: =IFERROR(J32/I32-1,0) -> 0.17142197 | K33: =IFERROR(K32/J32-1,0) -> 0.15748353
A35: Reported FY25 revenue (₹ Cr) | F35: 342
A36: Model FY25 (calc) | F36: =F32 -> 325.70192
A37: Variance vs. reported | F37: =(F32-F35)/F35 -> -0.047655205
A39: REVENUE MIX (%)
A41: MDR / Acquiring | C41: =C10/C32 -> 0.73243589 | D41: =D10/D32 -> 0.69314218 | E41: =E10/E32 -> 0.65125539 | F41: =F10/F32 -> 0.61787146 | G41: =G10/G32 -> 0.60303724 | H41: =H10/H32 -> 0.5907799 | I41: =I10/I32 -> 0.57417272 | J41: =J10/J32 -> 0.55761903 | K41: =K10/K32 -> 0.54884783
A42: Mcapital / Lending | C42: =C16/C32 -> 0.043512389 | D42: =D16/D32 -> 0.06001231 | E42: =E16/E32 -> 0.084946355 | F42: =F16/F32 -> 0.10334603 | G42: =G16/G32 -> 0.13224501 | H42: =H16/H32 -> 0.15269012 | I42: =I16/I32 -> 0.17149723 | J42: =J16/J32 -> 0.18966634 | K42: =K16/K32 -> 0.20579221
A43: Terminal sales | C43: =C22/C32 -> 0.13906659 | D43: =D22/D32 -> 0.14960334 | E43: =E22/E32 -> 0.15761531 | F43: =F22/F32 -> 0.1535146 | G43: =G22/G32 -> 0.13614622 | H43: =H22/H32 -> 0.1222969 | I43: =I22/I32 -> 0.11651978 | J43: =J22/J32 -> 0.11222106 | K43: =K22/K32 -> 0.1038778
A44: VAS / Subscription | C44: =C28/C32 -> 0.084985135 | D44: =D28/D32 -> 0.097242169 | E44: =E28/E32 -> 0.10618294 | F44: =F28/F32 -> 0.12526791 | G44: =G28/G32 -> 0.12857154 | H44: =H28/H32 -> 0.13423308 | I44: =I28/I32 -> 0.13781027 | J44: =J28/J32 -> 0.14049358 | K44: =K28/K32 -> 0.14148215

Sheet 4. Cost Build
A1: Mswipe — Cost Build
A2: Variable + fixed cost stack; reconciles to historical EBITDA.
C4: FY22A | D4: FY23A | E4: FY24A | F4: FY25A | G4: FY26E | H4: FY27E | I4: FY28E | J4: FY29E | K4: FY30E
A6: VARIABLE COSTS
A8: MDR revenue (₹ Cr) | C8: ='3. Revenue Build'!C10 -> 118.503 | D8: ='3. Revenue Build'!D10 -> 145.9458 | E8: ='3. Revenue Build'!E10 -> 176.64 | F8: ='3. Revenue Build'!F10 -> 201.24192 | G8: ='3. Revenue Build'!G10 -> 243.61344 | H8: ='3. Revenue Build'!H10 -> 289.84213 | I8: ='3. Revenue Build'!I10 -> 336.31447 | J8: ='3. Revenue Build'!J10 -> 382.60792 | K8: ='3. Revenue Build'!K10 -> 435.89626
A9: Variable cost ratio | C9: ='2. Operating Assumptions'!C37 -> 0.35 | D9: ='2. Operating Assumptions'!D37 -> 0.34 | E9: ='2. Operating Assumptions'!E37 -> 0.33 | F9: ='2. Operating Assumptions'!F37 -> 0.32 | G9: ='2. Operating Assumptions'!G37 -> 0.3 | H9: ='2. Operating Assumptions'!H37 -> 0.28 | I9: ='2. Operating Assumptions'!I37 -> 0.27 | J9: ='2. Operating Assumptions'!J37 -> 0.26 | K9: ='2. Operating Assumptions'!K37 -> 0.25
A10: Interchange + scheme + processing | C10: =C8*C9 -> 41.47605 | D10: =D8*D9 -> 49.621572 | E10: =E8*E9 -> 58.2912 | F10: =F8*F9 -> 64.397414 | G10: =G8*G9 -> 73.084032 | H10: =H8*H9 -> 81.155798 | I10: =I8*I9 -> 90.804908 | J10: =J8*J9 -> 99.478058 | K10: =K8*K9 -> 108.97407
A12: Terminal revenue (₹ Cr) | C12: ='3. Revenue Build'!C22 -> 22.5 | D12: ='3. Revenue Build'!D22 -> 31.5 | E12: ='3. Revenue Build'!E22 -> 42.75 | F12: ='3. Revenue Build'!F22 -> 50 | G12: ='3. Revenue Build'!G22 -> 55 | H12: ='3. Revenue Build'!H22 -> 60 | I12: ='3. Revenue Build'!I22 -> 68.25 | J12: ='3. Revenue Build'!J22 -> 77 | K12: ='3. Revenue Build'!K22 -> 82.5
A13: Terminal COGS ratio | C13: ='2. Operating Assumptions'!C38 -> 0.78 | D13: ='2. Operating Assumptions'!D38 -> 0.78 | E13: ='2. Operating Assumptions'!E38 -> 0.78 | F13: ='2. Operating Assumptions'!F38 -> 0.78 | G13: ='2. Operating Assumptions'!G38 -> 0.78 | H13: ='2. Operating Assumptions'!H38 -> 0.78 | I13: ='2. Operating Assumptions'!I38 -> 0.78 | J13: ='2. Operating Assumptions'!J38 -> 0.78 | K13: ='2. Operating Assumptions'!K38 -> 0.78
A14: Terminal COGS | C14: =C12*C13 -> 17.55 | D14: =D12*D13 -> 24.57 | E14: =E12*E13 -> 33.345 | F14: =F12*F13 -> 39 | G14: =G12*G13 -> 42.9 | H14: =H12*H13 -> 46.8 | I14: =I12*I13 -> 53.235 | J14: =J12*J13 -> 60.06 | K14: =K12*K13 -> 64.35
A16: Total variable costs | C16: =C10+C14 -> 59.02605 | D16: =D10+D14 -> 74.191572 | E16: =E10+E14 -> 91.6362 | F16: =F10+F14 -> 103.39741 | G16: =G10+G14 -> 115.98403 | H16: =H10+H14 -> 127.9558 | I16: =I10+I14 -> 144.03991 | J16: =J10+J14 -> 159.53806 | K16: =K10+K14 -> 173.32407
A18: FIXED / OPERATING COSTS
A20: Employee cost (₹ Cr) | C20: ='2. Operating Assumptions'!C39 -> 85 | D20: ='2. Operating Assumptions'!D39 -> 100 | E20: ='2. Operating Assumptions'!E39 -> 115 | F20: ='2. Operating Assumptions'!F39 -> 130 | G20: ='2. Operating Assumptions'!G39 -> 150 | H20: ='2. Operating Assumptions'!H39 -> 175 | I20: ='2. Operating Assumptions'!I39 -> 200 | J20: ='2. Operating Assumptions'!J39 -> 225 | K20: ='2. Operating Assumptions'!K39 -> 250
A21: Other opex (₹ Cr) | C21: ='2. Operating Assumptions'!C40 -> 45 | D21: ='2. Operating Assumptions'!D40 -> 55 | E21: ='2. Operating Assumptions'!E40 -> 70 | F21: ='2. Operating Assumptions'!F40 -> 80 | G21: ='2. Operating Assumptions'!G40 -> 92 | H21: ='2. Operating Assumptions'!H40 -> 108 | I21: ='2. Operating Assumptions'!I40 -> 128 | J21: ='2. Operating Assumptions'!J40 -> 150 | K21: ='2. Operating Assumptions'!K40 -> 175
A22: Total fixed costs | C22: =C20+C21 -> 130 | D22: =D20+D21 -> 155 | E22: =E20+E21 -> 185 | F22: =F20+F21 -> 210 | G22: =G20+G21 -> 242 | H22: =H20+H21 -> 283 | I22: =I20+I21 -> 328 | J22: =J20+J21 -> 375 | K22: =K20+K21 -> 425
A24: TOTAL COSTS
A26: Total operating costs | C26: =C16+C22 -> 189.02605 | D26: =D16+D22 -> 229.19157 | E26: =E16+E22 -> 276.6362 | F26: =F16+F22 -> 313.39741 | G26: =G16+G22 -> 357.98403 | H26: =H16+H22 -> 410.9558 | I26: =I16+I22 -> 472.03991 | J26: =J16+J22 -> 534.53806 | K26: =K16+K22 -> 598.32407
A28: Cost as % of revenue | C28: =C26/'3. Revenue Build'!C32 -> 1.1683203 | D28: =D26/'3. Revenue Build'!D32 -> 1.0885024 | E28: =E26/'3. Revenue Build'!E32 -> 1.0199322 | F28: =F26/'3. Revenue Build'!F32 -> 0.96222157 | G28: =G26/'3. Revenue Build'!G32 -> 0.88614857 | H28: =H26/'3. Revenue Build'!H32 -> 0.83764366 | I28: =I26/'3. Revenue Build'!I32 -> 0.8058899 | J28: =J26/'3. Revenue Build'!J32 -> 0.77904449 | K28: =K26/'3. Revenue Build'!K32 -> 0.75336473

Sheet 5. P&L Forecast
A1: Mswipe — Income Statement
A2: P&L FY22–FY30. Historical (FY22–FY25) bridged to forecast (FY26–FY30).
C4: FY22A | D4: FY23A | E4: FY24A | F4: FY25A | G4: FY26E | H4: FY27E | I4: FY28E | J4: FY29E | K4: FY30E
A6: Revenue | C6: ='3. Revenue Build'!C32 -> 161.793 | D6: ='3. Revenue Build'!D32 -> 210.5568 | E6: ='3. Revenue Build'!E32 -> 271.23 | F6: ='3. Revenue Build'!F32 -> 325.70192 | G6: ='3. Revenue Build'!G32 -> 403.97744 | H6: ='3. Revenue Build'!H32 -> 490.60933 | I6: ='3. Revenue Build'!I32 -> 585.73747 | J6: ='3. Revenue Build'!J32 -> 686.14574 | K6: ='3. Revenue Build'!K32 -> 794.20239
A7: Revenue growth (YoY) | D7: =IFERROR(D6/C6-1,0) -> 0.30139623 | E7: =IFERROR(E6/D6-1,0) -> 0.28815598 | F7: =IFERROR(F6/E6-1,0) -> 0.20083295 | G7: =IFERROR(G6/F6-1,0) -> 0.2403287 | H7: =IFERROR(H6/G6-1,0) -> 0.21444736 | I7: =IFERROR(I6/H6-1,0) -> 0.19389793 | J7: =IFERROR(J6/I6-1,0) -> 0.17142197 | K7: =IFERROR(K6/J6-1,0) -> 0.15748353
A9: REPORTED (BENCHMARK)
A11: Reported revenue (₹ Cr) | C11: 230 | D11: 274 | E11: 277 | F11: 342 | L11: MCA filings + Tracxn
A12: Model variance | C12: =IFERROR(C6/C11-1,0) -> -0.29655217 | D12: =IFERROR(D6/D11-1,0) -> -0.23154453 | E12: =IFERROR(E6/E11-1,0) -> -0.020830325 | F12: =IFERROR(F6/F11-1,0) -> -0.047655205
A14: OPERATING EXPENSES
A16: Variable costs | C16: ='4. Cost Build'!C16 -> 59.02605 | D16: ='4. Cost Build'!D16 -> 74.191572 | E16: ='4. Cost Build'!E16 -> 91.6362 | F16: ='4. Cost Build'!F16 -> 103.39741 | G16: ='4. Cost Build'!G16 -> 115.98403 | H16: ='4. Cost Build'!H16 -> 127.9558 | I16: ='4. Cost Build'!I16 -> 144.03991 | J16: ='4. Cost Build'!J16 -> 159.53806 | K16: ='4. Cost Build'!K16 -> 173.32407
A17: Fixed costs | C17: ='4. Cost Build'!C22 -> 130 | D17: ='4. Cost Build'!D22 -> 155 | E17: ='4. Cost Build'!E22 -> 185 | F17: ='4. Cost Build'!F22 -> 210 | G17: ='4. Cost Build'!G22 -> 242 | H17: ='4. Cost Build'!H22 -> 283 | I17: ='4. Cost Build'!I22 -> 328 | J17: ='4. Cost Build'!J22 -> 375 | K17: ='4. Cost Build'!K22 -> 425
A18: Total operating costs | C18: =C16+C17 -> 189.02605 | D18: =D16+D17 -> 229.19157 | E18: =E16+E17 -> 276.6362 | F18: =F16+F17 -> 313.39741 | G18: =G16+G17 -> 357.98403 | H18: =H16+H17 -> 410.9558 | I18: =I16+I17 -> 472.03991 | J18: =J16+J17 -> 534.53806 | K18: =K16+K17 -> 598.32407
A20: EBITDA | C20: =C6-C18 -> -27.23305 | D20: =D6-D18 -> -18.634772 | E20: =E6-E18 -> -5.4062 | F20: =F6-F18 -> 12.304506 | G20: =G6-G18 -> 45.993408 | H20: =H6-H18 -> 79.653537 | I20: =I6-I18 -> 113.69756 | J20: =J6-J18 -> 151.60768 | K20: =K6-K18 -> 195.87832
A21: EBITDA margin | C21: =IFERROR(C20/C6,0) -> -0.16832032 | D21: =IFERROR(D20/D6,0) -> -0.088502352 | E21: =IFERROR(E20/E6,0) -> -0.019932161 | F21: =IFERROR(F20/F6,0) -> 0.037778425 | G21: =IFERROR(G20/G6,0) -> 0.11385143 | H21: =IFERROR(H20/H6,0) -> 0.16235634 | I21: =IFERROR(I20/I6,0) -> 0.1941101 | J21: =IFERROR(J20/J6,0) -> 0.22095551 | K21: =IFERROR(K20/K6,0) -> 0.24663527
A23: D&A (% of revenue) | C23: ='2. Operating Assumptions'!C41 -> 0.1 | D23: ='2. Operating Assumptions'!D41 -> 0.09 | E23: ='2. Operating Assumptions'!E41 -> 0.08 | F23: ='2. Operating Assumptions'!F41 -> 0.08 | G23: ='2. Operating Assumptions'!G41 -> 0.07 | H23: ='2. Operating Assumptions'!H41 -> 0.07 | I23: ='2. Operating Assumptions'!I41 -> 0.07 | J23: ='2. Operating Assumptions'!J41 -> 0.06 | K23: ='2. Operating Assumptions'!K41 -> 0.06
A24: D&A | C24: =C6*C23 -> 16.1793 | D24: =D6*D23 -> 18.950112 | E24: =E6*E23 -> 21.6984 | F24: =F6*F23 -> 26.056154 | G24: =G6*G23 -> 28.278421 | H24: =H6*H23 -> 34.342653 | I24: =I6*I23 -> 41.001623 | J24: =J6*J23 -> 41.168744 | K24: =K6*K23 -> 47.652143
A26: EBIT | C26: =C20-C24 -> -43.41235 | D26: =D20-D24 -> -37.584884 | E26: =E20-E24 -> -27.1046 | F26: =F20-F24 -> -13.751648 | G26: =G20-G24 -> 17.714987 | H26: =H20-H24 -> 45.310883 | I26: =I20-I24 -> 72.695936 | J26: =J20-J24 -> 110.43893 | K26: =K20-K24 -> 148.22618
A27: EBIT margin | C27: =IFERROR(C26/C6,0) -> -0.26832032 | D27: =IFERROR(D26/D6,0) -> -0.17850235 | E27: =IFERROR(E26/E6,0) -> -0.099932161 | F27: =IFERROR(F26/F6,0) -> -0.042221575 | G27: =IFERROR(G26/G6,0) -> 0.043851427 | H27: =IFERROR(H26/H6,0) -> 0.092356342 | I27: =IFERROR(I26/I6,0) -> 0.1241101 | J27: =IFERROR(J26/J6,0) -> 0.16095551 | K27: =IFERROR(K26/K6,0) -> 0.18663527
A29: Effective tax rate | C29: ='2. Operating Assumptions'!C44 -> 0 | D29: ='2. Operating Assumptions'!D44 -> 0 | E29: ='2. Operating Assumptions'!E44 -> 0 | F29: ='2. Operating Assumptions'!F44 -> 0 | G29: ='2. Operating Assumptions'!G44 -> 0 | H29: ='2. Operating Assumptions'!H44 -> 0.05 | I29: ='2. Operating Assumptions'!I44 -> 0.15 | J29: ='2. Operating Assumptions'!J44 -> 0.22 | K29: ='2. Operating Assumptions'!K44 -> 0.25
A30: Tax | C30: =MAX(0,C26)*C29 -> 0 | D30: =MAX(0,D26)*D29 -> 0 | E30: =MAX(0,E26)*E29 -> 0 | F30: =MAX(0,F26)*F29 -> 0 | G30: =MAX(0,G26)*G29 -> 0 | H30: =MAX(0,H26)*H29 -> 2.2655442 | I30: =MAX(0,I26)*I29 -> 10.90439 | J30: =MAX(0,J26)*J29 -> 24.296565 | K30: =MAX(0,K26)*K29 -> 37.056545
A31: NOPAT (EBIT × (1−t)) | C31: =C26-C30 -> -43.41235 | D31: =D26-D30 -> -37.584884 | E31: =E26-E30 -> -27.1046 | F31: =F26-F30 -> -13.751648 | G31: =G26-G30 -> 17.714987 | H31: =H26-H30 -> 43.045339 | I31: =I26-I30 -> 61.791545 | J31: =J26-J30 -> 86.142368 | K31: =K26-K30 -> 111.16964
A33: UNLEVERED FREE CASH FLOW
A35: NOPAT | C35: =C31 -> -43.41235 | D35: =D31 -> -37.584884 | E35: =E31 -> -27.1046 | F35: =F31 -> -13.751648 | G35: =G31 -> 17.714987 | H35: =H31 -> 43.045339 | I35: =I31 -> 61.791545 | J35: =J31 -> 86.142368 | K35: =K31 -> 111.16964
A36: + D&A | C36: =C24 -> 16.1793 | D36: =D24 -> 18.950112 | E36: =E24 -> 21.6984 | F36: =F24 -> 26.056154 | G36: =G24 -> 28.278421 | H36: =H24 -> 34.342653 | I36: =I24 -> 41.001623 | J36: =J24 -> 41.168744 | K36: =K24 -> 47.652143
A37: − Capex | C37: =-C6*'2. Operating Assumptions'!C42 -> -19.41516 | D37: =-D6*'2. Operating Assumptions'!D42 -> -21.05568 | E37: =-E6*'2. Operating Assumptions'!E42 -> -21.6984 | F37: =-F6*'2. Operating Assumptions'!F42 -> -22.799134 | G37: =-G6*'2. Operating Assumptions'!G42 -> -24.238646 | H37: =-H6*'2. Operating Assumptions'!H42 -> -29.43656 | I37: =-I6*'2. Operating Assumptions'!I42 -> -29.286873 | J37: =-J6*'2. Operating Assumptions'!J42 -> -34.307287 | K37: =-K6*'2. Operating Assumptions'!K42 -> -39.710119
A38: − Δ NWC | C38: =0 -> 0 | D38: =-(D6-C6)*'2. Operating Assumptions'!D43 -> -4.87638 | E38: =-(E6-D6)*'2. Operating Assumptions'!E43 -> -6.06732 | F38: =-(F6-E6)*'2. Operating Assumptions'!F43 -> -5.447192 | G38: =-(G6-F6)*'2. Operating Assumptions'!G43 -> -7.827552 | H38: =-(H6-G6)*'2. Operating Assumptions'!H43 -> -8.6631894 | I38: =-(I6-H6)*'2. Operating Assumptions'!I43 -> -9.5128132 | J38: =-(J6-I6)*'2. Operating Assumptions'!J43 -> -10.040827 | K38: =-(K6-J6)*'2. Operating Assumptions'!K43 -> -10.805665
A40: Unlevered FCF | C40: =C35+C36+C37+C38 -> -46.64821 | D40: =D35+D36+D37+D38 -> -44.566832 | E40: =E35+E36+E37+E38 -> -33.17192 | F40: =F35+F36+F37+F38 -> -15.941821 | G40: =G35+G36+G37+G38 -> 13.92721 | H40: =H35+H36+H37+H38 -> 39.288243 | I40: =I35+I36+I37+I38 -> 63.993481 | J40: =J35+J36+J37+J38 -> 82.962999 | K40: =K35+K36+K37+K38 -> 108.30599
A41: FCF margin | C41: =IFERROR(C40/C6,0) -> -0.28832032 | D41: =IFERROR(D40/D6,0) -> -0.2116618 | E41: =IFERROR(E40/E6,0) -> -0.12230181 | F41: =IFERROR(F40/F6,0) -> -0.048946045 | G41: =IFERROR(G40/G6,0) -> 0.034475216 | H41: =IFERROR(H40/H6,0) -> 0.080080505 | I41: =IFERROR(I40/I6,0) -> 0.10925284 | J41: =IFERROR(J40/J6,0) -> 0.12091163 | K41: =IFERROR(K40/K6,0) -> 0.13637077

Sheet 6. DCF Valuation
A1: Mswipe — DCF Valuation
A2: Discounted unlevered FCF + Gordon Growth terminal. Sensitivity on next tab.
C4: FY26E | D4: FY27E | E4: FY28E | F4: FY29E | G4: FY30E | H4: Terminal
A6: Year (n) — mid-year convention | C6: =1-0.5 -> 0.5 | D6: =2-0.5 -> 1.5 | E6: =3-0.5 -> 2.5 | F6: =4-0.5 -> 3.5 | G6: =5-0.5 -> 4.5
A7: Discount factor | C7: =1/((1+'2. Operating Assumptions'!C48)^C6) -> 0.94072087 | D7: =1/((1+'2. Operating Assumptions'!C48)^D6) -> 0.83249634 | E7: =1/((1+'2. Operating Assumptions'!C48)^E6) -> 0.73672243 | F7: =1/((1+'2. Operating Assumptions'!C48)^F6) -> 0.65196675 | G7: =1/((1+'2. Operating Assumptions'!C48)^G6) -> 0.57696173
A9: DCF — STANDALONE
A11: Unlevered FCF (₹ Cr) | C11: ='5. P&L Forecast'!G40 -> 13.92721 | D11: ='5. P&L Forecast'!H40 -> 39.288243 | E11: ='5. P&L Forecast'!I40 -> 63.993481 | F11: ='5. P&L Forecast'!J40 -> 82.962999 | G11: ='5. P&L Forecast'!K40 -> 108.30599
A12: PV of FCF | C12: =C11*C7 -> 13.101617 | D12: =D11*D7 -> 32.707319 | E12: =E11*E7 -> 47.145433 | F12: =F11*F7 -> 54.089117 | G12: =G11*G7 -> 62.488413
A14: Terminal year FCF (year 5) | H14: =G11*(1+'2. Operating Assumptions'!C49) -> 112.63823
A15: Terminal value (Gordon Growth) | H15: =H14/('2. Operating Assumptions'!C48-'2. Operating Assumptions'!C49) -> 1251.5359
A16: PV of terminal value | H16: =H15*G7 -> 722.08833
A19: VALUATION SUMMARY
A21: Sum of PV of explicit FCF | C21: =SUM(C12:G12) -> 209.5319
A22: PV of terminal value | C22: =H16 -> 722.08833
A23: Enterprise value | C23: =C21+C22 -> 931.62023
A25: PV explicit / EV | C25: =C21/C23 -> 0.22491128
A26: PV terminal / EV | C26: =C22/C23 -> 0.77508872
A28: Less: Net debt (Mswipe, ₹ Cr) | C28: -50
A29: Equity value | C29: =C23-C28 -> 981.62023
A31: IMPLIED MULTIPLES — STANDALONE
A33: EV / FY25 revenue | C33: =C23/'5. P&L Forecast'!F6 -> 2.8603461
A34: EV / FY26E revenue | C34: =C23/'5. P&L Forecast'!G6 -> 2.3061194
A35: EV / FY27E EBITDA | C35: =C23/MAX(1,'5. P&L Forecast'!H20) -> 11.695905
A38: VALUE WITH SYNERGIES TO ACQUIRER
A40: Cost synergies — run-rate (₹ Cr) | C40: 160
A41: Revenue synergies — run-rate (₹ Cr) | C41: 120
A42: Synergy EBITDA margin | C42: 0.5
A43: Total run-rate synergy EBITDA (₹ Cr) | C43: =C40+C41*C42 -> 220
A44: PV of synergies (5y, ramp 0/30/65/90/100%, 12% disc) | C44: =SUMPRODUCT({0,0.3,0.65,0.9,1}*C43*(1/((1+'2. Operating Assumptions'!C48)^{0.5,1.5,2.5,3.5,4.5}))) -> 416.31706
A45: + PV terminal synergy (post-tax @75%) | C45: =C43*0.75/('2. Operating Assumptions'!C48-'2. Operating Assumptions'!C49)*1/((1+'2. Operating Assumptions'!C48)^4.5) -> 1057.7632
A46: Total synergy NPV (₹ Cr) | C46: =C44+C45 -> 1474.0802
A48: Standalone equity value | C48: =C29 -> 981.62023
A49: + Synergy NPV (to acquirer pre-share) | C49: =C46 -> 1474.0802
A50: − Share of synergy to seller | C50: =-C49*'2. Operating Assumptions'!C53 -> -368.52006
A51: + Control premium | C51: =C48*'2. Operating Assumptions'!C52 -> 98.162023
A52: Indicative offer envelope (₹ Cr) | C52: =C48+C49+C50+C51 -> 2185.3424

Sheet 7. Trading Comps
A1: Trading Comparables — Listed Payments / Fintech
A2: Multiples-based view; Mswipe valuation by analogy.
A4: Company | B4: Geo | C4: Market cap ($M) | D4: EV ($M) | E4: Revenue ($M) | F4: EBITDA ($M) | G4: Rev growth | H4: EBITDA margin | I4: EV/Revenue | J4: EV/EBITDA | K4: Notes
A5: Pine Labs | B5: India | C5: 2900 | D5: 2800 | E5: 280 | F5: 35 | G5: 0.28 | H5: 0.13 | I5: =D5/E5 -> 10 | J5: =IFERROR(D5/F5,0) -> 80 | K5: Listed Nov 2025, ~₹25K Cr mcap
A6: PayTM (One97) | B6: India | C6: 7200 | D6: 6800 | E6: 800 | F6: 80 | G6: 0.1 | H6: 0.1 | I6: =D6/E6 -> 8.5 | J6: =IFERROR(D6/F6,0) -> 85 | K6: Recovering from regulatory issues
A7: Razorpay | B7: India | C7: 7500 | D7: 7500 | E7: 380 | F7: 30 | G7: 0.4 | H7: 0.08 | I7: =D7/E7 -> 19.736842 | J7: =IFERROR(D7/F7,0) -> 250 | K7: Pre-IPO, last priced 2022
A8: Cashfree Payments | B8: India | C8: 700 | D8: 650 | E8: 130 | F8: 13 | G8: 0.5 | H8: 0.1 | I8: =D8/E8 -> 5 | J8: =IFERROR(D8/F8,0) -> 50 | K8: Pre-IPO, late-stage
A9: InfoBeans / Innoviti | B9: India | C9: 200 | D9: 180 | E9: 85 | F9: 4 | G9: 0.15 | H9: 0.05 | I9: =D9/E9 -> 2.1176471 | J9: =IFERROR(D9/F9,0) -> 45 | K9: POS player, smaller scale
A10: Worldline (FR) | B10: Europe | C10: 4200 | D10: 8500 | E10: 4800 | F10: 1100 | G10: 0.04 | H10: 0.23 | I10: =D10/E10 -> 1.7708333 | J10: =IFERROR(D10/F10,0) -> 7.7272727 | K10: Listed; recent comp deteriorating
A11: Adyen NV | B11: Europe | C11: 45000 | D11: 42000 | E11: 2400 | F11: 1100 | G11: 0.22 | H11: 0.46 | I11: =D11/E11 -> 17.5 | J11: =IFERROR(D11/F11,0) -> 38.181818 | K11: Best-in-class scale + margin
A12: Block (Square) | B12: US | C12: 50000 | D12: 52000 | E12: 24500 | F12: 1800 | G12: 0.1 | H12: 0.07 | I12: =D12/E12 -> 2.122449 | J12: =IFERROR(D12/F12,0) -> 28.888889 | K12: Diversified beyond merchant
A13: Fiserv | B13: US | C13: 100000 | D13: 128000 | E13: 21000 | F13: 8500 | G13: 0.07 | H13: 0.4 | I13: =D13/E13 -> 6.0952381 | J13: =IFERROR(D13/F13,0) -> 15.058824 | K13: Mature large-cap processor
A14: Global Payments | B14: US | C14: 27000 | D14: 38000 | E14: 10500 | F14: 4500 | G14: 0.05 | H14: 0.43 | I14: =D14/E14 -> 3.6190476 | J14: =IFERROR(D14/F14,0) -> 8.4444444 | K14: Mature, merchant + issuer
A16: STATS
A17: Mean | G17: =AVERAGE(G5:G14) -> 0.191 | H17: =AVERAGE(H5:H14) -> 0.205 | I17: =AVERAGE(I5:I14) -> 7.6462057 | J17: =AVERAGE(J5:J14) -> 60.830125
A18: Median | G18: =MEDIAN(G5:G14) -> 0.125 | H18: =MEDIAN(H5:H14) -> 0.115 | I18: =MEDIAN(I5:I14) -> 5.547619 | J18: =MEDIAN(J5:J14) -> 41.590909
A19: Min | G19: =MIN(G5:G14) -> 0.04 | H19: =MIN(H5:H14) -> 0.05 | I19: =MIN(I5:I14) -> 1.7708333 | J19: =MIN(J5:J14) -> 7.7272727
A20: Max | G20: =MAX(G5:G14) -> 0.5 | H20: =MAX(H5:H14) -> 0.46 | I20: =MAX(I5:I14) -> 19.736842 | J20: =MAX(J5:J14) -> 250
A21: 25th %ile | G21: =QUARTILE(G5:G14,1) -> 0.0775 | H21: =QUARTILE(H5:H14,1) -> 0.085 | I21: =QUARTILE(I5:I14,1) -> 2.4965986 | J21: =QUARTILE(J5:J14,1) -> 18.51634
A22: 75th %ile | G22: =QUARTILE(G5:G14,3) -> 0.265 | H22: =QUARTILE(H5:H14,3) -> 0.3575 | I22: =QUARTILE(I5:I14,3) -> 9.625 | J22: =QUARTILE(J5:J14,3) -> 72.5
A24: INDIA PEERS ONLY
A25: Mean | G25: =AVERAGE(G5:G9) -> 0.286 | H25: =AVERAGE(H5:H9) -> 0.092 | I25: =AVERAGE(I5:I9) -> 9.0708978 | J25: =AVERAGE(J5:J9) -> 102
A26: Median | G26: =MEDIAN(G5:G9) -> 0.28 | H26: =MEDIAN(H5:H9) -> 0.1 | I26: =MEDIAN(I5:I9) -> 8.5 | J26: =MEDIAN(J5:J9) -> 80
A28: IMPLIED MSWIPE VALUATION BY COMP MULTIPLES
A30: Mswipe FY25 revenue (₹ Cr) | E30: ='5. P&L Forecast'!F6 -> 325.70192
A31: Mswipe FY26E revenue (₹ Cr) | E31: ='5. P&L Forecast'!G6 -> 403.97744
A33: EV/Rev multiple range applied | J33: EV on FY25 (₹ Cr) | K33: EV on FY26E (₹ Cr)
A34: India peers median × 0.5 (asset-reset discount) | I34: =I26*0.5 -> 4.25 | J34: =I34*E30 -> 1384.2332 | K34: =I34*E31 -> 1716.9041
A35: India peers median × 0.6 | I35: =I26*0.6 -> 5.1 | J35: =I35*E30 -> 1661.0798 | K35: =I35*E31 -> 2060.2849
A36: India peers median × 0.7 | I36: =I26*0.7 -> 5.95 | J36: =I36*E30 -> 1937.9264 | K36: =I36*E31 -> 2403.6658
A37: India peers median × 0.85 | I37: =I26*0.85 -> 7.225 | J37: =I37*E30 -> 2353.1964 | K37: =I37*E31 -> 2918.737
A39: Indicative trading-comp range (FY25): ₹400–700 Cr

Sheet 8. Transaction Comps
A1: Precedent Transactions — Payments M&A
A2: Recent deals in India + comparable global mPOS / payments transactions.
A4: Year | B4: Acquirer | C4: Target | D4: Deal value ($M) | E4: Target revenue ($M) | F4: Target EBITDA ($M) | G4: EV/Revenue | H4: EV/EBITDA | I4: Geo | J4: Notes
A5: 2025 | B5: Pine Labs | C5: Mosambee | D5: 50 | E5: 40 | F5: 2 | G5: =IFERROR(D5/E5,0) -> 1.25 | H5: =IFERROR(D5/F5,0) -> 25 | I5: India | J5: Strategic tuck-in for offline acquiring (illustrative)
A6: 2024 | B6: PhonePe | C6: OPGSP | D6: 80 | E6: 35 | F6: 1 | G6: =IFERROR(D6/E6,0) -> 2.2857143 | H6: =IFERROR(D6/F6,0) -> 80 | I6: India | J6: Offline merchant acquisition; control deal
A7: 2024 | B7: Innoviti | C7: PayMate | D7: 120 | E7: 45 | F7: 2 | G7: =IFERROR(D7/E7,0) -> 2.6666667 | H7: =IFERROR(D7/F7,0) -> 60 | I7: India | J7: B2B payments + offline POS combo
A8: 2023 | B8: PayU India | C8: BillDesk* | D8: 0 | E8: 320 | F8: 60 | G8: =IFERROR(D8/E8,0) -> 0 | H8: =IFERROR(D8/F8,0) -> 0 | I8: India | J8: Deal called off — antitrust
A9: 2023 | B9: Lightspeed | C9: Vend NZ | D9: 430 | E9: 95 | F9: 5 | G9: =IFERROR(D9/E9,0) -> 4.5263158 | H9: =IFERROR(D9/F9,0) -> 86 | I9: Global | J9: SaaS + payments adjacency
A10: 2023 | B10: Worldline | C10: Bambora India | D10: 35 | E10: 20 | F10: 0 | G10: =IFERROR(D10/E10,0) -> 1.75 | H10: =IFERROR(D10/F10,0) -> 0 | I10: India | J10: Distressed sale of mPOS network
A11: 2022 | B11: Block (Square) | C11: Afterpay | D11: 29000 | E11: 1300 | F11: 100 | G11: =IFERROR(D11/E11,0) -> 22.307692 | H11: =IFERROR(D11/F11,0) -> 290 | I11: Global | J11: BNPL strategic; pre-rate-shock
A12: 2022 | B12: FIS | C12: Worldpay** | D12: 17500 | E12: 4900 | F12: 1100 | G12: =IFERROR(D12/E12,0) -> 3.5714286 | H12: =IFERROR(D12/F12,0) -> 15.909091 | I12: Global | J12: Largest payments comp; FIS later divested
A13: 2021 | B13: PayU | C13: BillDesk (deal) | D13: 4700 | E13: 240 | F13: 45 | G13: =IFERROR(D13/E13,0) -> 19.583333 | H13: =IFERROR(D13/F13,0) -> 104.44444 | I13: India | J13: Largest India fintech deal; later terminated
A14: 2021 | B14: Mastercard | C14: Finicity | D14: 825 | E14: 45 | F14: 8 | G14: =IFERROR(D14/E14,0) -> 18.333333 | H14: =IFERROR(D14/F14,0) -> 103.125 | I14: Global | J14: Account-aggregation tuck-in
A16: INDIA-ONLY TRANSACTION STATS
A18: Mean | G18: =AVERAGE(G5,G6,G7,G8,G10,G13) -> 4.5892857 | H18: =AVERAGE(H5,H6,H7,H8,H10,H13) -> 44.907407
A19: Median | G19: =MEDIAN(G5,G6,G7,G8,G10,G13) -> 2.0178571 | H19: =MEDIAN(H5,H6,H7,H8,H10,H13) -> 42.5
A20: Min | G20: =MIN(G5,G6,G7,G8,G10,G13) -> 0 | H20: =MIN(H5,H6,H7,H8,H10,H13) -> 0
A21: Max | G21: =MAX(G5,G6,G7,G8,G10,G13) -> 19.583333 | H21: =MAX(H5,H6,H7,H8,H10,H13) -> 104.44444
A23: IMPLIED MSWIPE VALUATION — TRANSACTION COMPS
A25: Mswipe FY25 revenue (₹ Cr) | E25: ='5. P&L Forecast'!F6 -> 325.70192
A27: EV/Rev multiple applied | I27: Implied EV (₹ Cr)
A28: India median | G28: =G19 -> 2.0178571 | I28: =G28*E25 -> 657.21995
A29: India mean | G29: =G18 -> 4.5892857 | I29: =G29*E25 -> 1494.7392
A30: India median + 25% | G30: =G19*1.25 -> 2.5223214 | I30: =G30*E25 -> 821.52493
A32: * / ** Indicates deals that were terminated or modified

Sheet 9. Football Field
A1: Mswipe Valuation — Football Field
A2: Cross-methodology valuation range with recommended bid envelope.
A4: Methodology | B4: Approach | C4: Low (₹ Cr) | D4: High (₹ Cr) | E4: Range
A5: DCF — standalone (base) | B5: Cross-sheet DCF | C5: 850 | D5: 1100 | E5: ₹850–1,100 Cr
A6: DCF + 50% synergy share | B6: PV synergy × 50% to seller | C6: 1500 | D6: 1900 | E6: ₹1,500–1,900 Cr
A7: Trading comps (India peers) | B7: 0.5–0.85× peer EV/Rev | C7: 1100 | D7: 1800 | E7: ₹1,100–1,800 Cr
A8: Transaction comps (India) | B8: Median to +25% | C8: 1400 | D8: 2100 | E8: ₹1,400–2,100 Cr
A9: Last priced round (2017) | B9: $210M × INR82 | C9: 1500 | D9: 1700 | E9: ₹1,500–1,700 Cr
A10: Distressed / liquidation | B10: 0.8× book + tech | C10: 700 | D10: 1100 | E10: ₹700–1,100 Cr
A12: RECOMMENDED OFFER ENVELOPE
A13: Initial bid (low end) | C13: 1800 | E13: ₹1,800 Cr
A14: Walk-away (high end) | C14: 2400 | E14: ₹2,400 Cr
A15: Base case (mid) | C15: 2100 | E15: ₹2,100 Cr
A18: VALUATION DECISION FRAMEWORK
A20: 1. Standalone DCF (₹850–1,100 Cr) reflects current distressed trajectory and growth uncertainty
A21: 2. India transaction-comp median (~5–6× EV/Rev) supports ₹1,800–2,100 Cr at FY25 revenue
A22: 3. 50% share of run-rate synergy NPV (~₹1,200 Cr) adds ~₹600 Cr premium above standalone DCF
A23: 4. CCI clearance risk and integration risk argue for tighter (lower-end) bid at ₹1,800 Cr
A24: 5. Strategic optionality (offline consolidation + Mcapital) justifies walking up to ₹2,400 Cr
A25: 6. Final bid expected in ₹1,950–2,150 Cr range; cash-stock 50/50 to share execution risk

Sheet 10. Deal Structure
A1: Deal Structure — Sources & Uses
A2: Indicative funding structure for Mswipe acquisition.
A4: SOURCES OF FUNDS | B4: Amount (₹ Cr) | C4: % of total | D4: Cost (%) | F4: USES OF FUNDS | G4: Amount (₹ Cr) | H4: % of total
A6: Cash on hand (IPO proceeds) | B6: 1000 | C6: =B6/B10 -> 0.47619048 | D6: 0.04 | F6: Cash consideration to Mswipe shareholders | G6: 1000 | H6: =G6/G12 -> 0.47619048
A7: New equity issuance to seller | B7: 1000 | C7: =B7/B10 -> 0.47619048 | D7: 0 | F7: Stock consideration to Mswipe shareholders | G7: 1000 | H7: =G7/G12 -> 0.47619048
A8: Term loan (5-yr, SOFR+250) | B8: 100 | C8: =B8/B10 -> 0.047619048 | D8: 0.085 | F8: Transaction fees (advisory, legal, regulatory) | G8: 30 | H8: =G8/G12 -> 0.014285714
F9: Financing fees & expenses | G9: 5 | H9: =G9/G12 -> 0.0023809524
A10: Total sources | B10: =SUM(B6:B8) -> 2100 | F10: Retention pool (top 100 employees, 3-yr vest) | G10: 65 | H10: =G10/G12 -> 0.030952381
F12: Total uses | G12: =SUM(G6:G10) -> 2100
A14: Sources – Uses (must equal zero) | B14: =B10-G12 -> 0
A17: DEAL MECHANICS
A19: Total transaction value (₹ Cr) | B19: =B10-30-5-65 -> 2000
A20: Cash component (₹ Cr) | B20: =1000 -> 1000
A21: Stock component (₹ Cr) | B21: =1000 -> 1000
A22: Cash / Stock split (%) | B22: =1000/(1000+1000) -> 0.5
A23: Pine Labs share price (at deal) | B23: =280 -> 280
A24: New shares issued (mn) | B24: =1000*100/280/10 -> 35.714286
A25: Pre-deal Pine Labs shares (mn) | B25: =1130 -> 1130
A26: Pro-forma shares (mn) | B26: =1130+1000*100/280/10 -> 1165.7143
A27: Dilution to existing shareholders | B27: =(1000*100/280/10)/(1130+1000*100/280/10) -> 0.030637255

Sheet 11. Sensitivity
A1: Sensitivity Analysis
A2: Two-way tables — DCF EV sensitivity to WACC × TGR and operating drivers.
A4: DCF EV (₹ Cr) — WACC × Terminal Growth
A6: WACC → | B6: 0.1 | C6: 0.11 | D6: 0.12 | E6: 0.13 | F6: 0.14 | G6: 0.15 | H6: 0.16
A7: 0.02 | B7: ='5. P&L Forecast'!G40/((1+$B$6)^0.5)+'5. P&L Forecast'!H40/((1+$B$6)^1.5)+'5. P&L Forecast'!I40/((1+$B$6)^2.5)+'5. P&L Forecast'!J40/((1+$B$6)^3.5)+'5. P&L Forecast'!K40/((1+$B$6)^4.5)+'5. P&L Forecast'!K40*(1+$A$7)/($B$6-$A$7)/((1+$B$6)^4.5) -> 1127.0033 | C7: ='5. P&L Forecast'!G40/((1+$C$6)^0.5)+'5. P&L Forecast'!H40/((1+$C$6)^1.5)+'5. P&L Forecast'!I40/((1+$C$6)^2.5)+'5. P&L Forecast'!J40/((1+$C$6)^3.5)+'5. P&L Forecast'!K40/((1+$C$6)^4.5)+'5. P&L Forecast'!K40*(1+$A$7)/($C$6-$A$7)/((1+$C$6)^4.5) -> 988.86892 | D7: ='5. P&L Forecast'!G40/((1+$D$6)^0.5)+'5. P&L Forecast'!H40/((1+$D$6)^1.5)+'5. P&L Forecast'!I40/((1+$D$6)^2.5)+'5. P&L Forecast'!J40/((1+$D$6)^3.5)+'5. P&L Forecast'!K40/((1+$D$6)^4.5)+'5. P&L Forecast'!K40*(1+$A$7)/($D$6-$A$7)/((1+$D$6)^4.5) -> 878.74218 | E7: ='5. P&L Forecast'!G40/((1+$E$6)^0.5)+'5. P&L Forecast'!H40/((1+$E$6)^1.5)+'5. P&L Forecast'!I40/((1+$E$6)^2.5)+'5. P&L Forecast'!J40/((1+$E$6)^3.5)+'5. P&L Forecast'!K40/((1+$E$6)^4.5)+'5. P&L Forecast'!K40*(1+$A$7)/($E$6-$A$7)/((1+$E$6)^4.5) -> 788.96991 | F7: ='5. P&L Forecast'!G40/((1+$F$6)^0.5)+'5. P&L Forecast'!H40/((1+$F$6)^1.5)+'5. P&L Forecast'!I40/((1+$F$6)^2.5)+'5. P&L Forecast'!J40/((1+$F$6)^3.5)+'5. P&L Forecast'!K40/((1+$F$6)^4.5)+'5. P&L Forecast'!K40*(1+$A$7)/($F$6-$A$7)/((1+$F$6)^4.5) -> 714.45075 | G7: ='5. P&L Forecast'!G40/((1+$G$6)^0.5)+'5. P&L Forecast'!H40/((1+$G$6)^1.5)+'5. P&L Forecast'!I40/((1+$G$6)^2.5)+'5. P&L Forecast'!J40/((1+$G$6)^3.5)+'5. P&L Forecast'!K40/((1+$G$6)^4.5)+'5. P&L Forecast'!K40*(1+$A$7)/($G$6-$A$7)/((1+$G$6)^4.5) -> 651.65357 | H7: ='5. P&L Forecast'!G40/((1+$H$6)^0.5)+'5. P&L Forecast'!H40/((1+$H$6)^1.5)+'5. P&L Forecast'!I40/((1+$H$6)^2.5)+'5. P&L Forecast'!J40/((1+$H$6)^3.5)+'5. P&L Forecast'!K40/((1+$H$6)^4.5)+'5. P&L Forecast'!K40*(1+$A$7)/($H$6-$A$7)/((1+$H$6)^4.5) -> 598.05667
A8: 0.03 | B8: ='5. P&L Forecast'!G40/((1+$B$6)^0.5)+'5. P&L Forecast'!H40/((1+$B$6)^1.5)+'5. P&L Forecast'!I40/((1+$B$6)^2.5)+'5. P&L Forecast'!J40/((1+$B$6)^3.5)+'5. P&L Forecast'!K40/((1+$B$6)^4.5)+'5. P&L Forecast'!K40*(1+$A$8)/($B$6-$A$8)/((1+$B$6)^4.5) -> 1265.548 | C8: ='5. P&L Forecast'!G40/((1+$C$6)^0.5)+'5. P&L Forecast'!H40/((1+$C$6)^1.5)+'5. P&L Forecast'!I40/((1+$C$6)^2.5)+'5. P&L Forecast'!J40/((1+$C$6)^3.5)+'5. P&L Forecast'!K40/((1+$C$6)^4.5)+'5. P&L Forecast'!K40*(1+$A$8)/($C$6-$A$8)/((1+$C$6)^4.5) -> 1093.2663 | D8: ='5. P&L Forecast'!G40/((1+$D$6)^0.5)+'5. P&L Forecast'!H40/((1+$D$6)^1.5)+'5. P&L Forecast'!I40/((1+$D$6)^2.5)+'5. P&L Forecast'!J40/((1+$D$6)^3.5)+'5. P&L Forecast'!K40/((1+$D$6)^4.5)+'5. P&L Forecast'!K40*(1+$A$8)/($D$6-$A$8)/((1+$D$6)^4.5) -> 959.67914 | E8: ='5. P&L Forecast'!G40/((1+$E$6)^0.5)+'5. P&L Forecast'!H40/((1+$E$6)^1.5)+'5. P&L Forecast'!I40/((1+$E$6)^2.5)+'5. P&L Forecast'!J40/((1+$E$6)^3.5)+'5. P&L Forecast'!K40/((1+$E$6)^4.5)+'5. P&L Forecast'!K40*(1+$A$8)/($E$6-$A$8)/((1+$E$6)^4.5) -> 853.16255 | F8: ='5. P&L Forecast'!G40/((1+$F$6)^0.5)+'5. P&L Forecast'!H40/((1+$F$6)^1.5)+'5. P&L Forecast'!I40/((1+$F$6)^2.5)+'5. P&L Forecast'!J40/((1+$F$6)^3.5)+'5. P&L Forecast'!K40/((1+$F$6)^4.5)+'5. P&L Forecast'!K40*(1+$A$8)/($F$6-$A$8)/((1+$F$6)^4.5) -> 766.32019 | G8: ='5. P&L Forecast'!G40/((1+$G$6)^0.5)+'5. P&L Forecast'!H40/((1+$G$6)^1.5)+'5. P&L Forecast'!I40/((1+$G$6)^2.5)+'5. P&L Forecast'!J40/((1+$G$6)^3.5)+'5. P&L Forecast'!K40/((1+$G$6)^4.5)+'5. P&L Forecast'!K40*(1+$A$8)/($G$6-$A$8)/((1+$G$6)^4.5) -> 694.22179 | H8: ='5. P&L Forecast'!G40/((1+$H$6)^0.5)+'5. P&L Forecast'!H40/((1+$H$6)^1.5)+'5. P&L Forecast'!I40/((1+$H$6)^2.5)+'5. P&L Forecast'!J40/((1+$H$6)^3.5)+'5. P&L Forecast'!K40/((1+$H$6)^4.5)+'5. P&L Forecast'!K40*(1+$A$8)/($H$6-$A$8)/((1+$H$6)^4.5) -> 633.45462
A9: 0.04 | B9: ='5. P&L Forecast'!G40/((1+$B$6)^0.5)+'5. P&L Forecast'!H40/((1+$B$6)^1.5)+'5. P&L Forecast'!I40/((1+$B$6)^2.5)+'5. P&L Forecast'!J40/((1+$B$6)^3.5)+'5. P&L Forecast'!K40/((1+$B$6)^4.5)+'5. P&L Forecast'!K40*(1+$A$9)/($B$6-$A$9)/((1+$B$6)^4.5) -> 1450.2743 | C9: ='5. P&L Forecast'!G40/((1+$C$6)^0.5)+'5. P&L Forecast'!H40/((1+$C$6)^1.5)+'5. P&L Forecast'!I40/((1+$C$6)^2.5)+'5. P&L Forecast'!J40/((1+$C$6)^3.5)+'5. P&L Forecast'!K40/((1+$C$6)^4.5)+'5. P&L Forecast'!K40*(1+$A$9)/($C$6-$A$9)/((1+$C$6)^4.5) -> 1227.4915 | D9: ='5. P&L Forecast'!G40/((1+$D$6)^0.5)+'5. P&L Forecast'!H40/((1+$D$6)^1.5)+'5. P&L Forecast'!I40/((1+$D$6)^2.5)+'5. P&L Forecast'!J40/((1+$D$6)^3.5)+'5. P&L Forecast'!K40/((1+$D$6)^4.5)+'5. P&L Forecast'!K40*(1+$A$9)/($D$6-$A$9)/((1+$D$6)^4.5) -> 1060.8503 | E9: ='5. P&L Forecast'!G40/((1+$E$6)^0.5)+'5. P&L Forecast'!H40/((1+$E$6)^1.5)+'5. P&L Forecast'!I40/((1+$E$6)^2.5)+'5. P&L Forecast'!J40/((1+$E$6)^3.5)+'5. P&L Forecast'!K40/((1+$E$6)^4.5)+'5. P&L Forecast'!K40*(1+$A$9)/($E$6-$A$9)/((1+$E$6)^4.5) -> 931.62023 | F9: ='5. P&L Forecast'!G40/((1+$F$6)^0.5)+'5. P&L Forecast'!H40/((1+$F$6)^1.5)+'5. P&L Forecast'!I40/((1+$F$6)^2.5)+'5. P&L Forecast'!J40/((1+$F$6)^3.5)+'5. P&L Forecast'!K40/((1+$F$6)^4.5)+'5. P&L Forecast'!K40*(1+$A$9)/($F$6-$A$9)/((1+$F$6)^4.5) -> 828.56352 | G9: ='5. P&L Forecast'!G40/((1+$G$6)^0.5)+'5. P&L Forecast'!H40/((1+$G$6)^1.5)+'5. P&L Forecast'!I40/((1+$G$6)^2.5)+'5. P&L Forecast'!J40/((1+$G$6)^3.5)+'5. P&L Forecast'!K40/((1+$G$6)^4.5)+'5. P&L Forecast'!K40*(1+$A$9)/($G$6-$A$9)/((1+$G$6)^4.5) -> 744.52968 | H9: ='5. P&L Forecast'!G40/((1+$H$6)^0.5)+'5. P&L Forecast'!H40/((1+$H$6)^1.5)+'5. P&L Forecast'!I40/((1+$H$6)^2.5)+'5. P&L Forecast'!J40/((1+$H$6)^3.5)+'5. P&L Forecast'!K40/((1+$H$6)^4.5)+'5. P&L Forecast'!K40*(1+$A$9)/($H$6-$A$9)/((1+$H$6)^4.5) -> 674.75224
A10: 0.05 | B10: ='5. P&L Forecast'!G40/((1+$B$6)^0.5)+'5. P&L Forecast'!H40/((1+$B$6)^1.5)+'5. P&L Forecast'!I40/((1+$B$6)^2.5)+'5. P&L Forecast'!J40/((1+$B$6)^3.5)+'5. P&L Forecast'!K40/((1+$B$6)^4.5)+'5. P&L Forecast'!K40*(1+$A$10)/($B$6-$A$10)/((1+$B$6)^4.5) -> 1708.8912 | C10: ='5. P&L Forecast'!G40/((1+$C$6)^0.5)+'5. P&L Forecast'!H40/((1+$C$6)^1.5)+'5. P&L Forecast'!I40/((1+$C$6)^2.5)+'5. P&L Forecast'!J40/((1+$C$6)^3.5)+'5. P&L Forecast'!K40/((1+$C$6)^4.5)+'5. P&L Forecast'!K40*(1+$A$10)/($C$6-$A$10)/((1+$C$6)^4.5) -> 1406.4584 | D10: ='5. P&L Forecast'!G40/((1+$D$6)^0.5)+'5. P&L Forecast'!H40/((1+$D$6)^1.5)+'5. P&L Forecast'!I40/((1+$D$6)^2.5)+'5. P&L Forecast'!J40/((1+$D$6)^3.5)+'5. P&L Forecast'!K40/((1+$D$6)^4.5)+'5. P&L Forecast'!K40*(1+$A$10)/($D$6-$A$10)/((1+$D$6)^4.5) -> 1190.9276 | E10: ='5. P&L Forecast'!G40/((1+$E$6)^0.5)+'5. P&L Forecast'!H40/((1+$E$6)^1.5)+'5. P&L Forecast'!I40/((1+$E$6)^2.5)+'5. P&L Forecast'!J40/((1+$E$6)^3.5)+'5. P&L Forecast'!K40/((1+$E$6)^4.5)+'5. P&L Forecast'!K40*(1+$A$10)/($E$6-$A$10)/((1+$E$6)^4.5) -> 1029.6923 | F10: ='5. P&L Forecast'!G40/((1+$F$6)^0.5)+'5. P&L Forecast'!H40/((1+$F$6)^1.5)+'5. P&L Forecast'!I40/((1+$F$6)^2.5)+'5. P&L Forecast'!J40/((1+$F$6)^3.5)+'5. P&L Forecast'!K40/((1+$F$6)^4.5)+'5. P&L Forecast'!K40*(1+$A$10)/($F$6-$A$10)/((1+$F$6)^4.5) -> 904.63871 | G10: ='5. P&L Forecast'!G40/((1+$G$6)^0.5)+'5. P&L Forecast'!H40/((1+$G$6)^1.5)+'5. P&L Forecast'!I40/((1+$G$6)^2.5)+'5. P&L Forecast'!J40/((1+$G$6)^3.5)+'5. P&L Forecast'!K40/((1+$G$6)^4.5)+'5. P&L Forecast'!K40*(1+$A$10)/($G$6-$A$10)/((1+$G$6)^4.5) -> 804.89915 | H10: ='5. P&L Forecast'!G40/((1+$H$6)^0.5)+'5. P&L Forecast'!H40/((1+$H$6)^1.5)+'5. P&L Forecast'!I40/((1+$H$6)^2.5)+'5. P&L Forecast'!J40/((1+$H$6)^3.5)+'5. P&L Forecast'!K40/((1+$H$6)^4.5)+'5. P&L Forecast'!K40*(1+$A$10)/($H$6-$A$10)/((1+$H$6)^4.5) -> 723.5585
A11: 0.06 | B11: ='5. P&L Forecast'!G40/((1+$B$6)^0.5)+'5. P&L Forecast'!H40/((1+$B$6)^1.5)+'5. P&L Forecast'!I40/((1+$B$6)^2.5)+'5. P&L Forecast'!J40/((1+$B$6)^3.5)+'5. P&L Forecast'!K40/((1+$B$6)^4.5)+'5. P&L Forecast'!K40*(1+$A$11)/($B$6-$A$11)/((1+$B$6)^4.5) -> 2096.8165 | C11: ='5. P&L Forecast'!G40/((1+$C$6)^0.5)+'5. P&L Forecast'!H40/((1+$C$6)^1.5)+'5. P&L Forecast'!I40/((1+$C$6)^2.5)+'5. P&L Forecast'!J40/((1+$C$6)^3.5)+'5. P&L Forecast'!K40/((1+$C$6)^4.5)+'5. P&L Forecast'!K40*(1+$A$11)/($C$6-$A$11)/((1+$C$6)^4.5) -> 1657.0121 | D11: ='5. P&L Forecast'!G40/((1+$D$6)^0.5)+'5. P&L Forecast'!H40/((1+$D$6)^1.5)+'5. P&L Forecast'!I40/((1+$D$6)^2.5)+'5. P&L Forecast'!J40/((1+$D$6)^3.5)+'5. P&L Forecast'!K40/((1+$D$6)^4.5)+'5. P&L Forecast'!K40*(1+$A$11)/($D$6-$A$11)/((1+$D$6)^4.5) -> 1364.364 | E11: ='5. P&L Forecast'!G40/((1+$E$6)^0.5)+'5. P&L Forecast'!H40/((1+$E$6)^1.5)+'5. P&L Forecast'!I40/((1+$E$6)^2.5)+'5. P&L Forecast'!J40/((1+$E$6)^3.5)+'5. P&L Forecast'!K40/((1+$E$6)^4.5)+'5. P&L Forecast'!K40*(1+$A$11)/($E$6-$A$11)/((1+$E$6)^4.5) -> 1155.785 | F11: ='5. P&L Forecast'!G40/((1+$F$6)^0.5)+'5. P&L Forecast'!H40/((1+$F$6)^1.5)+'5. P&L Forecast'!I40/((1+$F$6)^2.5)+'5. P&L Forecast'!J40/((1+$F$6)^3.5)+'5. P&L Forecast'!K40/((1+$F$6)^4.5)+'5. P&L Forecast'!K40*(1+$A$11)/($F$6-$A$11)/((1+$F$6)^4.5) -> 999.73268 | G11: ='5. P&L Forecast'!G40/((1+$G$6)^0.5)+'5. P&L Forecast'!H40/((1+$G$6)^1.5)+'5. P&L Forecast'!I40/((1+$G$6)^2.5)+'5. P&L Forecast'!J40/((1+$G$6)^3.5)+'5. P&L Forecast'!K40/((1+$G$6)^4.5)+'5. P&L Forecast'!K40*(1+$A$11)/($G$6-$A$11)/((1+$G$6)^4.5) -> 878.68406 | H11: ='5. P&L Forecast'!G40/((1+$H$6)^0.5)+'5. P&L Forecast'!H40/((1+$H$6)^1.5)+'5. P&L Forecast'!I40/((1+$H$6)^2.5)+'5. P&L Forecast'!J40/((1+$H$6)^3.5)+'5. P&L Forecast'!K40/((1+$H$6)^4.5)+'5. P&L Forecast'!K40*(1+$A$11)/($H$6-$A$11)/((1+$H$6)^4.5) -> 782.12603
A14: FY30 EBITDA (₹ Cr) — Take rate × Merchant growth
A16: Take rate (bps) → | B16: 13 | C16: 15 | D16: 17 | E16: 19 | F16: 21 | G16: 23 | H16: 25
A17: 0.03 | B17: =(700*(1+$A$17)^5*1.27*290*12/100*$B$16/10000)*(1-0.53)+120-195 -> -53.086672 | C17: =(700*(1+$A$17)^5*1.27*290*12/100*$C$16/10000)*(1-0.53)+120-195 -> -49.715391 | D17: =(700*(1+$A$17)^5*1.27*290*12/100*$D$16/10000)*(1-0.53)+120-195 -> -46.34411 | E17: =(700*(1+$A$17)^5*1.27*290*12/100*$E$16/10000)*(1-0.53)+120-195 -> -42.972828 | F17: =(700*(1+$A$17)^5*1.27*290*12/100*$F$16/10000)*(1-0.53)+120-195 -> -39.601547 | G17: =(700*(1+$A$17)^5*1.27*290*12/100*$G$16/10000)*(1-0.53)+120-195 -> -36.230266 | H17: =(700*(1+$A$17)^5*1.27*290*12/100*$H$16/10000)*(1-0.53)+120-195 -> -32.858985
A18: 0.05 | B18: =(700*(1+$A$18)^5*1.27*290*12/100*$B$16/10000)*(1-0.53)+120-195 -> -50.874923 | C18: =(700*(1+$A$18)^5*1.27*290*12/100*$C$16/10000)*(1-0.53)+120-195 -> -47.163373 | D18: =(700*(1+$A$18)^5*1.27*290*12/100*$D$16/10000)*(1-0.53)+120-195 -> -43.451822 | E18: =(700*(1+$A$18)^5*1.27*290*12/100*$E$16/10000)*(1-0.53)+120-195 -> -39.740272 | F18: =(700*(1+$A$18)^5*1.27*290*12/100*$F$16/10000)*(1-0.53)+120-195 -> -36.028722 | G18: =(700*(1+$A$18)^5*1.27*290*12/100*$G$16/10000)*(1-0.53)+120-195 -> -32.317171 | H18: =(700*(1+$A$18)^5*1.27*290*12/100*$H$16/10000)*(1-0.53)+120-195 -> -28.605621
A19: 0.07 | B19: =(700*(1+$A$19)^5*1.27*290*12/100*$B$16/10000)*(1-0.53)+120-195 -> -48.488085 | C19: =(700*(1+$A$19)^5*1.27*290*12/100*$C$16/10000)*(1-0.53)+120-195 -> -44.409329 | D19: =(700*(1+$A$19)^5*1.27*290*12/100*$D$16/10000)*(1-0.53)+120-195 -> -40.330572 | E19: =(700*(1+$A$19)^5*1.27*290*12/100*$E$16/10000)*(1-0.53)+120-195 -> -36.251816 | F19: =(700*(1+$A$19)^5*1.27*290*12/100*$F$16/10000)*(1-0.53)+120-195 -> -32.17306 | G19: =(700*(1+$A$19)^5*1.27*290*12/100*$G$16/10000)*(1-0.53)+120-195 -> -28.094304 | H19: =(700*(1+$A$19)^5*1.27*290*12/100*$H$16/10000)*(1-0.53)+120-195 -> -24.015548
A20: 0.09 | B20: =(700*(1+$A$20)^5*1.27*290*12/100*$B$16/10000)*(1-0.53)+120-195 -> -45.915962 | C20: =(700*(1+$A$20)^5*1.27*290*12/100*$C$16/10000)*(1-0.53)+120-195 -> -41.441495 | D20: =(700*(1+$A$20)^5*1.27*290*12/100*$D$16/10000)*(1-0.53)+120-195 -> -36.967027 | E20: =(700*(1+$A$20)^5*1.27*290*12/100*$E$16/10000)*(1-0.53)+120-195 -> -32.49256 | F20: =(700*(1+$A$20)^5*1.27*290*12/100*$F$16/10000)*(1-0.53)+120-195 -> -28.018092 | G20: =(700*(1+$A$20)^5*1.27*290*12/100*$G$16/10000)*(1-0.53)+120-195 -> -23.543625 | H20: =(700*(1+$A$20)^5*1.27*290*12/100*$H$16/10000)*(1-0.53)+120-195 -> -19.069158
A21: 0.11 | B21: =(700*(1+$A$21)^5*1.27*290*12/100*$B$16/10000)*(1-0.53)+120-195 -> -43.147971 | C21: =(700*(1+$A$21)^5*1.27*290*12/100*$C$16/10000)*(1-0.53)+120-195 -> -38.247658 | D21: =(700*(1+$A$21)^5*1.27*290*12/100*$D$16/10000)*(1-0.53)+120-195 -> -33.347346 | E21: =(700*(1+$A$21)^5*1.27*290*12/100*$E$16/10000)*(1-0.53)+120-195 -> -28.447034 | F21: =(700*(1+$A$21)^5*1.27*290*12/100*$F$16/10000)*(1-0.53)+120-195 -> -23.546722 | G21: =(700*(1+$A$21)^5*1.27*290*12/100*$G$16/10000)*(1-0.53)+120-195 -> -18.646409 | H21: =(700*(1+$A$21)^5*1.27*290*12/100*$H$16/10000)*(1-0.53)+120-195 -> -13.746097
A24: Highlighted cells = base case assumption.
A25: Sensitivity #2 holds lending, terminal sales, VAS revenue and fixed costs constant at base-case values.
